{"skeleton":{"hash":"Z7m8VPBGnHM","spine":"4.1.24","x":-925.93,"y":-434,"width":1867.13,"height":923.22,"images":"../images/","audio":"D:/2d/slot/circus/wins/Epic_Win/images"},"bones":[{"name":"root","scaleX":0.5,"scaleY":0.5},{"name":"main","parent":"root","color":"ffffffff"},{"name":"epic_win","parent":"main","color":"1eff00ff"},{"name":"epic","parent":"epic_win","x":2.02,"y":1.02,"color":"ff0000ff"},{"name":"win","parent":"epic_win","x":1.92,"y":1,"color":"ff0000ff"},{"name":"glows","parent":"root"},{"name":"star_mask","parent":"epic_win","x":-1964.92,"y":-535.2,"color":"1eff00ff"}],"slots":[{"name":"green smoke1","bone":"glows","attachment":"green smoke"},{"name":"green smoke2","bone":"glows","attachment":"green smoke"},{"name":"back desiogn","bone":"main","attachment":"back desiogn"},{"name":"Star_BG","bone":"main","attachment":"Star_BG"},{"name":"star_glow","bone":"star_mask","attachment":"star_glow"},{"name":"Star_Glow","bone":"main","attachment":"Star_Glow","blend":"additive"},{"name":"Win_Shadow","bone":"win","attachment":"Win_Shadow"},{"name":"Epic_Shadow","bone":"epic","attachment":"Epic_Shadow"},{"name":"Bulb_Off_L","bone":"main","attachment":"Bulb_Off_L"},{"name":"Bulb_Off_R","bone":"main","attachment":"Bulb_Off_R"},{"name":"Bulb_Off_Bottom","bone":"main","attachment":"Bulb_Off_Bottom"},{"name":"Bulb_Off_Top","bone":"main","attachment":"Bulb_Off_Top"},{"name":"Bulb_on_01_L","bone":"main","attachment":"Bulb_on_01_L"},{"name":"Bulb_on_01_R","bone":"main","attachment":"Bulb_on_01_R"},{"name":"Bulb_on_01_Buttom","bone":"main","attachment":"Bulb_on_01_Buttom"},{"name":"Bulb_on_01_Top","bone":"main","attachment":"Bulb_on_01_Top"},{"name":"Bulb_on_02_L","bone":"main","attachment":"Bulb_on_02_L"},{"name":"Bulb_on_02_R","bone":"main","attachment":"Bulb_on_02_R"},{"name":"Bulb_on_02_Bottom","bone":"main","attachment":"Bulb_on_02_Bottom"},{"name":"Bulb_on_02_Top","bone":"main","attachment":"Bulb_on_02_Top"},{"name":"smoke_2","bone":"glows","attachment":"Effects_02"},{"name":"smoke_2.2","bone":"glows","attachment":"Effects_02"},{"name":"Effects_01","bone":"glows","attachment":"Effects_01","blend":"screen"},{"name":"Win","bone":"win","attachment":"Win"},{"name":"Epic","bone":"epic","attachment":"Epic"},{"name":"win_glow","bone":"main","attachment":"Layer 143 copy 2","blend":"additive"},{"name":"epic_glow","bone":"main","attachment":"Layer 143 copy 2","blend":"additive"}],"skins":[{"name":"default","attachments":{"back desiogn":{"back desiogn":{"type":"mesh","uvs":[1,1,0,1,0,0,1,0],"triangles":[1,2,3,1,3,0],"vertices":[1678,-580,-1676,-580,-1676,578,1678,578],"hull":4,"edges":[0,2,2,4,4,6,0,6],"width":1677,"height":579}},"Bulb_Off_Bottom":{"Bulb_Off_Bottom":{"type":"mesh","uvs":[1,1,0,1,0,0,1,0],"triangles":[1,2,3,1,3,0],"vertices":[970,-404,-1006,-404,-1006,-278,970,-278],"hull":4,"edges":[0,2,2,4,4,6,0,6],"width":988,"height":63}},"Bulb_Off_L":{"Bulb_Off_L":{"type":"mesh","uvs":[1,1,0,1,0,0,1,0],"triangles":[1,2,3,0,1,3],"vertices":[-1090,-348,-1276,-348,-1276,344,-1090,344],"hull":4,"edges":[0,2,2,4,4,6,0,6],"width":93,"height":346}},"Bulb_Off_R":{"Bulb_Off_R":{"type":"mesh","uvs":[1,1,0,1,0,0,1,0],"triangles":[1,2,3,0,1,3],"vertices":[1266,-358,1072,-358,1072,320,1266,320],"hull":4,"edges":[0,2,2,4,4,6,0,6],"width":97,"height":339}},"Bulb_Off_Top":{"Bulb_Off_Top":{"type":"mesh","uvs":[1,1,0,1,0,0,1,0],"triangles":[1,2,3,1,3,0],"vertices":[1074,276,-1020,276,-1020,400,1074,400],"hull":4,"edges":[0,2,2,4,4,6,0,6],"width":1047,"height":62}},"Bulb_on_01_Buttom":{"Bulb_on_01_Buttom":{"type":"mesh","uvs":[1,1,0,1,0,0,1,0],"triangles":[1,2,3,1,3,0],"vertices":[1282,-444,-1296,-444,-1296,-204,1282,-204],"hull":4,"edges":[0,2,2,4,4,6,0,6],"width":1289,"height":120}},"Bulb_on_01_L":{"Bulb_on_01_L":{"type":"mesh","uvs":[1,1,0,1,0,0,1,0],"triangles":[1,2,3,1,3,0],"vertices":[1290,-244,-1314,-244,-1314,384,1290,384],"hull":4,"edges":[0,2,2,4,4,6,0,6],"width":1302,"height":314}},"Bulb_on_01_R":{"Bulb_on_01_R":{"type":"mesh","uvs":[1,1,0,1,0,0,1,0],"triangles":[1,2,3,0,1,3],"vertices":[1308,-234,1070,-234,1070,358,1308,358],"hull":4,"edges":[0,2,2,4,4,6,0,6],"width":119,"height":296}},"Bulb_on_01_Top":{"Bulb_on_01_Top":{"type":"mesh","uvs":[1,1,0,1,0,0,1,0],"triangles":[1,2,3,1,3,0],"vertices":[1134,214,-1130,214,-1130,442,1134,442],"hull":4,"edges":[0,2,2,4,4,6,0,6],"width":1132,"height":114}},"Bulb_on_02_Bottom":{"Bulb_on_02_Bottom":{"type":"mesh","uvs":[1,1,0,1,0,0,1,0],"triangles":[1,2,3,1,3,0],"vertices":[1068,-442,-1084,-442,-1084,-240,1068,-240],"hull":4,"edges":[0,2,2,4,4,6,0,6],"width":1076,"height":101}},"Bulb_on_02_L":{"Bulb_on_02_L":{"type":"mesh","uvs":[1,1,0,1,0,0,1,0],"triangles":[1,2,3,0,1,3],"vertices":[-1080,-374,-1316,-374,-1316,184,-1080,184],"hull":4,"edges":[0,2,2,4,4,6,0,6],"width":118,"height":279}},"Bulb_on_02_R":{"Bulb_on_02_R":{"type":"mesh","uvs":[1,1,0,1,0,0,1,0],"triangles":[1,2,3,1,3,0],"vertices":[1310,-290,1016,-290,1016,402,1310,402],"hull":4,"edges":[0,2,2,4,4,6,0,6],"width":147,"height":346}},"Bulb_on_02_Top":{"Bulb_on_02_Top":{"type":"mesh","uvs":[1,1,0,1,0,0,1,0],"triangles":[1,2,3,1,3,0],"vertices":[906,180,-1270,180,-1270,436,906,436],"hull":4,"edges":[0,2,2,4,4,6,0,6],"width":1088,"height":128}},"Effects_01":{"Effects_01":{"type":"mesh","uvs":[1,1,0,1,0,0,1,0],"triangles":[1,2,3,1,3,0],"vertices":[1762,-614,-1706,-614,-1706,652,1762,652],"hull":4,"edges":[0,2,2,4,4,6,0,6],"width":1734,"height":633}},"Epic":{"Epic":{"type":"mesh","uvs":[1,1,0,1,0,0,1,0],"triangles":[1,2,3,1,3,0],"vertices":[-18.02,-267.02,-1146.02,-267.02,-1146.02,272.98,-18.02,272.98],"hull":4,"edges":[0,2,2,4,4,6,0,6],"width":564,"height":270}},"epic_glow":{"Layer 143 copy 2":{"type":"mesh","uvs":[0.50823,1,0,1,0,0,0.5063,0],"triangles":[1,2,3,1,3,0],"vertices":[1,3,-28.46,-277.02,1,1,3,-1112.02,-277.02,1,1,3,-1112.02,274.98,1,1,3,-32.58,274.98,1],"hull":4,"edges":[2,4,4,6,0,2,6,0],"width":1066,"height":276}},"Epic_Shadow":{"Epic_Shadow":{"type":"mesh","uvs":[1,1,0,1,0,0,1,0],"triangles":[1,2,3,1,3,0],"vertices":[-36.02,-297.02,-1092.02,-297.02,-1092.02,246.98,-36.02,246.98],"hull":4,"edges":[0,2,2,4,4,6,0,6],"width":528,"height":272}},"green smoke1":{"green smoke":{"type":"mesh","uvs":[0.32969,0.10873,0.40488,0.16893,0.48571,0.20047,0.58131,0.2117,0.65673,0.15186,0.76666,0.11857,0.84342,0.1718,0.92346,0.26354,0.9716,0.39268,0.9897,0.51934,0.98852,0.66543,0.96547,0.79839,0.88368,0.86744,0.80022,0.91545,0.69615,0.922,0.60711,0.91101,0.54014,0.89525,0.46234,0.89562,0.36069,0.90706,0.27193,0.93047,0.17843,0.93504,0.08808,0.88421,0.03797,0.73973,0.01825,0.56402,0.0194,0.39466,0.07949,0.29519,0.13797,0.21603,0.19999,0.12914,0.25883,0.08492,0.16915,0.37875,0.07403,0.47007,0.16432,0.52284,0.08234,0.5946,0.14329,0.58132,0.45099,0.33694,0.37618,0.33136,0.27166,0.26584,0.60916,0.31325,0.76112,0.29377,0.94372,0.45558,0.85011,0.33905,0.84122,0.51988,0.90057,0.4983,0.85439,0.58796,0.92366,0.5946,0.90426,0.69091,0.8073,0.79551,0.85809,0.83536,0.86918,0.78795,0.82001,0.84183,0.83107,0.80835,0.7739,0.83396,0.71581,0.80461,0.64342,0.83259,0.57128,0.80666,0.53028,0.8401,0.55572,0.83464,0.47105,0.79983,0.41904,0.81963,0.52231,0.7657,0.2642,0.8098,0.19323,0.85752,0.23169,0.85071,0.30754,0.78155,0.30808,0.84584,0.35196,0.79129,0.40126,0.76207,0.17305,0.73115,0.10533,0.75939,0.11779,0.74868,0.127,0.76037,0.07987,0.70874,0.05983,0.63861,0.30893,0.30176,0.20945,0.31404,0.53377,0.34064,0.67524,0.29734],"triangles":[36,28,0,27,28,36,38,4,5,38,5,6,76,4,38,37,3,4,73,36,0,73,0,1,76,37,4,74,27,36,26,27,74,35,73,1,34,1,2,35,1,34,40,6,7,38,6,40,75,2,3,75,3,37,34,2,75,29,26,74,25,26,29,39,7,8,40,7,39,30,24,25,30,25,29,42,40,39,39,8,9,41,38,40,41,40,42,31,30,29,23,24,30,33,30,31,43,41,42,32,30,33,23,30,32,44,42,39,44,39,9,43,42,44,72,23,32,10,44,9,45,43,44,45,44,10,71,72,32,74,31,29,63,67,31,33,31,67,22,23,72,22,72,71,33,71,32,69,33,67,69,71,33,68,71,69,70,69,67,66,35,34,59,66,34,75,59,34,73,74,36,63,73,35,63,35,66,73,31,74,73,63,31,48,43,45,65,63,66,38,41,76,43,52,41,46,43,48,11,45,10,48,45,11,57,66,59,41,52,76,43,46,52,37,59,75,54,59,37,37,76,52,53,54,37,50,46,48,60,67,63,58,66,57,52,53,37,51,52,46,56,59,54,47,50,48,55,59,56,57,59,55,49,46,50,51,46,49,64,63,65,60,63,64,62,67,60,61,67,62,70,67,61,12,48,11,47,48,12,68,22,71,21,22,68,16,55,56,17,58,57,17,57,55,17,55,16,58,18,65,58,65,66,64,65,18,18,58,17,15,54,53,56,54,15,16,56,15,13,51,49,47,13,49,47,49,50,13,47,12,14,53,52,15,53,14,14,52,51,14,51,13,19,60,64,62,60,19,19,64,18,61,21,70,20,61,62,20,62,19,68,69,70,70,21,68,61,20,21],"vertices":[-654.66,927.54,-365.62,798.82,-54.94,731.4,312.54,707.38,602.46,835.32,1025.02,906.5,1320.12,792.7,1627.8,596.56,1812.84,320.46,1882.4,49.66,1877.86,-262.68,1789.28,-546.94,1474.86,-694.58,1154.04,-797.24,754,-811.24,411.72,-787.72,154.3,-754.06,-144.78,-754.84,-535.5,-779.28,-876.7,-829.34,-1236.12,-839.1,-1583.42,-730.44,-1776.02,-421.54,-1851.86,-45.88,-1847.42,316.22,-1616.46,528.88,-1391.64,698.14,-1153.22,883.9,-927.08,978.44,-1271.78,350.24,-1637.44,154.98,-1290.36,42.18,-1605.48,-111.26,-1371.18,-82.86,-188.4,439.62,-475.98,451.56,-877.74,591.64,419.6,490.28,1003.74,531.9,1705.66,185.96,1345.82,435.1,1311.64,48.48,1539.8,94.64,1362.3,-97.06,1628.54,-111.26,1554,-317.16,1181.24,-540.8,1376.5,-626,1419.14,-524.64,1230.14,-639.84,1272.64,-568.26,1052.88,-623,829.58,-560.26,551.3,-620.08,274.02,-564.62,116.4,-636.14,214.18,-624.46,-111.28,-550.04,-311.2,-592.36,85.74,-477.06,-906.42,-571.34,-1179.22,-673.38,-1031.36,-658.8,-739.82,-510.96,-737.74,-648.4,-569.04,-531.78,-379.54,-469.3,-1256.78,-403.2,-1517.1,-463.58,-1469.2,-440.68,-1433.8,-465.66,-1614.98,-355.3,-1692.04,-205.36,-734.46,514.84,-1116.88,488.58,129.84,431.72,673.64,524.3],"hull":29,"edges":[0,56,2,4,12,14,16,18,18,20,24,26,30,32,32,34,36,38,38,40,40,42,42,44,44,46,46,48,48,50,50,52,52,54,54,56,34,36,28,30,4,6,0,2,26,28,20,22,6,8,8,10,10,12,14,16,22,24],"width":1922,"height":1069}},"green smoke2":{"green smoke":{"type":"mesh","uvs":[0.32969,0.10873,0.40488,0.16893,0.48571,0.20047,0.58131,0.2117,0.65673,0.15186,0.76666,0.11857,0.84342,0.1718,0.92346,0.26354,0.9716,0.39268,0.9897,0.51934,0.98852,0.66543,0.96547,0.79839,0.88368,0.86744,0.80022,0.91545,0.69615,0.922,0.60711,0.91101,0.54014,0.89525,0.46234,0.89562,0.36069,0.90706,0.27193,0.93047,0.17843,0.93504,0.08808,0.88421,0.03797,0.73973,0.01825,0.56402,0.0194,0.39466,0.07949,0.29519,0.13797,0.21603,0.19999,0.12914,0.25883,0.08492,0.16915,0.37875,0.07403,0.47007,0.16432,0.52284,0.08234,0.5946,0.14329,0.58132,0.45099,0.33694,0.37618,0.33136,0.27166,0.26584,0.60916,0.31325,0.76112,0.29377,0.94372,0.45558,0.85011,0.33905,0.84122,0.51988,0.90057,0.4983,0.85439,0.58796,0.92366,0.5946,0.90426,0.69091,0.8073,0.79551,0.85809,0.83536,0.86918,0.78795,0.82001,0.84183,0.83107,0.80835,0.7739,0.83396,0.71581,0.80461,0.64342,0.83259,0.57128,0.80666,0.53028,0.8401,0.55572,0.83464,0.47105,0.79983,0.41904,0.81963,0.52231,0.7657,0.2642,0.8098,0.19323,0.85752,0.23169,0.85071,0.30754,0.78155,0.30808,0.84584,0.35196,0.79129,0.40126,0.76207,0.17305,0.73115,0.10533,0.75939,0.11779,0.74868,0.127,0.76037,0.07987,0.70874,0.05983,0.63861,0.30893,0.30176,0.20945,0.31404,0.53377,0.34064,0.67524,0.29734],"triangles":[36,28,0,27,28,36,38,4,5,38,5,6,76,4,38,37,3,4,73,36,0,73,0,1,76,37,4,74,27,36,26,27,74,35,73,1,34,1,2,35,1,34,40,6,7,38,6,40,75,2,3,75,3,37,34,2,75,29,26,74,25,26,29,39,7,8,40,7,39,30,24,25,30,25,29,42,40,39,39,8,9,41,38,40,41,40,42,31,30,29,23,24,30,33,30,31,43,41,42,32,30,33,23,30,32,44,42,39,44,39,9,43,42,44,72,23,32,10,44,9,45,43,44,45,44,10,71,72,32,74,31,29,63,67,31,33,31,67,22,23,72,22,72,71,33,71,32,69,33,67,69,71,33,68,71,69,70,69,67,66,35,34,59,66,34,75,59,34,73,74,36,63,73,35,63,35,66,73,31,74,73,63,31,48,43,45,65,63,66,38,41,76,43,52,41,46,43,48,11,45,10,48,45,11,57,66,59,41,52,76,43,46,52,37,59,75,54,59,37,37,76,52,53,54,37,50,46,48,60,67,63,58,66,57,52,53,37,51,52,46,56,59,54,47,50,48,55,59,56,57,59,55,49,46,50,51,46,49,64,63,65,60,63,64,62,67,60,61,67,62,70,67,61,12,48,11,47,48,12,68,22,71,21,22,68,16,55,56,17,58,57,17,57,55,17,55,16,58,18,65,58,65,66,64,65,18,18,58,17,15,54,53,56,54,15,16,56,15,13,51,49,47,13,49,47,49,50,13,47,12,14,53,52,15,53,14,14,52,51,14,51,13,19,60,64,62,60,19,19,64,18,61,21,70,20,61,62,20,62,19,68,69,70,70,21,68,61,20,21],"vertices":[-654.66,927.54,-365.62,798.82,-54.94,731.4,312.54,707.38,602.46,835.32,1025.02,906.5,1320.12,792.7,1627.8,596.56,1812.84,320.46,1882.4,49.66,1877.86,-262.68,1789.28,-546.94,1474.86,-694.58,1154.04,-797.24,754,-811.24,411.72,-787.72,154.3,-754.06,-144.78,-754.84,-535.5,-779.28,-876.7,-829.34,-1236.12,-839.1,-1583.42,-730.44,-1776.02,-421.54,-1851.86,-45.88,-1847.42,316.22,-1616.46,528.88,-1391.64,698.14,-1153.22,883.9,-927.08,978.44,-1271.78,350.24,-1637.44,154.98,-1290.36,42.18,-1605.48,-111.26,-1371.18,-82.86,-188.4,439.62,-475.98,451.56,-877.74,591.64,419.6,490.28,1003.74,531.9,1705.66,185.96,1345.82,435.1,1311.64,48.48,1539.8,94.64,1362.3,-97.06,1628.54,-111.26,1554,-317.16,1181.24,-540.8,1376.5,-626,1419.14,-524.64,1230.14,-639.84,1272.64,-568.26,1052.88,-623,829.58,-560.26,551.3,-620.08,274.02,-564.62,116.4,-636.14,214.18,-624.46,-111.28,-550.04,-311.2,-592.36,85.74,-477.06,-906.42,-571.34,-1179.22,-673.38,-1031.36,-658.8,-739.82,-510.96,-737.74,-648.4,-569.04,-531.78,-379.54,-469.3,-1256.78,-403.2,-1517.1,-463.58,-1469.2,-440.68,-1433.8,-465.66,-1614.98,-355.3,-1692.04,-205.36,-734.46,514.84,-1116.88,488.58,129.84,431.72,673.64,524.3],"hull":29,"edges":[0,56,2,4,12,14,16,18,18,20,24,26,30,32,32,34,36,38,38,40,40,42,42,44,44,46,46,48,48,50,50,52,52,54,54,56,34,36,28,30,4,6,0,2,26,28,20,22,6,8,8,10,10,12,14,16,22,24],"width":1922,"height":1069}},"smoke_2":{"Effects_02":{"type":"mesh","uvs":[1,0.49346,1,1,0.61945,1,0.42654,1,0.34442,1,0.19098,1,0.08489,1,0,1,0,0.66316,0,0.45896,0,0,0.1888,0,0.32733,0,0.58916,0,0.6957,0,0.83771,0,1,0,0.22411,0.47167,0.39935,0.70307,0.09739,0.9081,0.17496,0.86472,0.14372,0.8989,0.16663,0.76744,0.19475,0.71354,0.20516,0.63729,0.21766,0.8358,0.26121,0.79636,0.31083,0.84128,0.28951,0.87524,0.33116,0.88181,0.32856,0.9436,0.07812,0.79636,0.04792,0.79767,0.04272,0.66621,0.02085,0.61363,0.05261,0.55315,0.05469,0.49925,0.83565,0.47107,0.65901,0.63639,0.52192,0.88954,0.55603,0.8706,0.54375,0.91709,0.59422,0.90159,0.62968,0.81549,0.67061,0.80516,0.71835,0.87404,0.69754,0.76077,0.74763,0.70788,0.79363,0.76767,0.83826,0.71247,0.85283,0.79182,0.89974,0.78837,0.94063,0.75797,0.94018,0.69013,0.96113,0.65333,0.98162,0.66138,0.85684,0.61194,0.84727,0.54064,0.7949,0.19021,0.76712,0.14997,0.73889,0.14307,0.7357,0.08212,0.70701,0.09707,0.69016,0.02808,0.67103,0.04303,0.66511,0.09592,0.59225,0.08672,0.59452,0.25806,0.68788,0.29945,0.76485,0.342,0.91103,0.14997,0.89874,0.28795,0.88097,0.41674,0.8154,0.3397,0.83134,0.22241,0.80356,0.12352,0.80993,0.02578,0.85957,0.06948,0.82633,0.09362,0.85411,0.13732,0.87141,0.20516,0.85547,0.2868,0.86595,0.35464,0.83589,0.04878,0.31267,0.31712,0.45987,0.41274,0.39814,0.26461,0.43542,0.31707,0.38837,0.17202,0.39142,0.08407,0.44215,0.10876,0.43176,0.20597,0.47026,0.24918,0.48065,0.36799,0.02323,0.08149,0.08599,0.07052,0.11351,0.13147,0.10627,0.18511,0.14489,0.14975,0.1642,0.19242,0.20476,0.25825,0.01792,0.15585,0.0633,0.1461,0.07199,0.21071,0.09516,0.28385,0.13427,0.23387,0.16613,0.2936,0.19193,0.0666,0.16444,0.07117,0.15286,0.11135,0.12645,0.10405,0.21797,0.04102,0.22919,0.09857,0.27079,0.09948,0.20278,0.1214,0.21906,0.20269,0.64461,0.09974],"triangles":[76,14,15,14,64,13,111,11,12,63,64,14,83,76,15,107,11,111,77,15,16,83,15,77,95,10,11,108,95,11,107,108,11,94,10,95,61,14,76,62,63,14,90,89,12,116,66,13,13,90,12,78,76,83,13,64,116,61,62,14,113,112,111,12,113,111,65,116,64,110,95,108,66,90,13,109,110,108,114,107,111,114,111,112,76,59,61,75,76,78,96,95,110,77,78,83,79,78,77,59,60,61,62,61,60,102,94,95,102,95,96,98,110,109,96,110,98,76,75,59,70,77,16,79,77,70,101,10,94,101,94,102,88,12,89,88,89,90,97,102,96,58,59,75,114,99,109,98,109,99,108,107,114,114,109,108,115,114,112,99,114,115,80,79,70,91,88,90,103,102,97,74,78,79,74,79,80,75,78,74,58,75,74,98,97,96,105,98,99,105,97,98,92,90,66,91,90,92,67,66,116,92,66,67,100,99,115,86,88,91,104,103,97,104,97,105,81,74,80,71,80,70,81,80,71,106,99,100,105,99,106,104,105,106,64,62,65,62,64,63,68,62,60,68,65,62,116,65,68,67,116,68,87,91,92,86,91,87,12,88,84,12,84,113,84,88,86,73,58,74,73,74,81,69,60,59,69,59,58,69,58,73,68,60,69,82,81,71,73,81,82,93,92,67,87,92,93,85,87,93,72,82,71,9,10,101,37,73,82,37,82,72,69,73,37,100,115,84,17,100,84,106,100,17,113,115,112,84,115,113,104,106,17,101,102,103,9,101,103,9,103,104,9,104,17,70,16,0,71,70,0,72,71,0,37,72,0,36,9,17,57,37,0,35,9,36,54,56,57,34,9,35,38,67,68,38,68,69,38,69,37,24,36,17,35,36,24,0,54,57,55,54,0,8,9,34,33,34,35,53,56,54,18,86,87,18,87,85,84,86,18,17,84,18,26,24,17,38,18,85,93,38,85,38,93,67,47,38,37,47,37,57,49,47,57,56,49,57,24,22,35,35,31,33,52,53,54,46,38,47,24,23,22,48,47,49,51,56,53,51,53,52,49,56,51,50,49,51,48,49,50,18,26,17,23,24,26,22,31,35,32,33,31,44,38,46,38,40,18,43,38,44,25,23,26,22,23,25,27,26,18,20,22,25,43,40,38,45,46,47,45,47,48,44,46,45,28,26,27,29,27,18,39,18,40,21,31,22,21,22,20,42,40,43,19,31,21,41,39,40,29,28,27,30,28,29,8,32,7,33,8,34,32,8,33,19,32,31,6,32,19,7,32,6,5,20,25,21,20,5,6,19,21,5,6,21,3,4,29,18,3,29,30,29,4,5,28,30,25,26,28,5,25,28,4,5,30,39,3,18,2,42,43,41,40,42,2,41,42,3,39,41,3,41,2,55,0,1,52,54,55,1,52,55,51,52,1,50,51,1,45,48,50,1,45,50,2,43,44,45,2,44,2,45,1],"vertices":[1732,-50.88,1732,-680,538.6,-680,-66.38,-680,-323.9,-680,-805.08,-680,-1137.78,-680,-1404,-680,-1404,-261.64,-1404,-8.02,-1404,562,-811.94,562,-377.48,562,443.6,562,777.72,562,1223.06,562,1732,562,-701.18,-23.82,-151.64,-311.22,-1098.6,-565.86,-855.32,-511.98,-953.28,-554.44,-881.44,-391.16,-793.28,-324.22,-760.62,-229.52,-721.42,-476.06,-584.84,-427.08,-429.24,-482.86,-496.1,-525.04,-365.48,-533.2,-373.64,-609.94,-1159.02,-427.08,-1253.72,-428.72,-1270.04,-265.44,-1338.62,-200.12,-1239.02,-125.02,-1232.48,-58.08,1216.62,-23.08,662.66,-228.4,232.76,-542.8,339.7,-519.28,301.22,-577.02,459.46,-557.78,570.68,-450.84,699.02,-438,848.74,-523.56,783.48,-382.88,940.58,-317.18,1084.82,-391.44,1224.78,-322.9,1270.48,-421.44,1417.58,-417.16,1545.82,-379.4,1544.4,-295.14,1610.1,-249.44,1674.36,-259.44,1283.04,-198.02,1253.06,-109.48,1088.82,325.76,1001.7,375.74,913.16,384.32,903.16,460,813.18,441.44,760.34,527.12,700.36,508.56,681.8,442.86,453.28,454.28,460.44,241.5,753.2,190.08,994.56,137.24,1453,375.74,1414.44,204.36,1358.74,44.42,1153.08,140.1,1203.06,285.76,1115.96,408.58,1135.94,529.98,1291.62,475.72,1187.36,445.72,1274.48,391.46,1328.74,307.2,1278.76,205.8,1311.6,121.54,1217.34,501.42,-423.46,168.14,38.14,49.38,-155.42,233.36,-38.52,168.2,-186.08,348.34,-176.5,457.58,-17.44,426.92,-50.02,306.18,70.72,252.52,103.3,104.96,-1331.16,460.8,-1134.34,474.42,-1048.04,398.72,-1070.74,332.1,-949.62,376,-889.06,323.02,-761.88,241.26,-1347.82,368.44,-1205.5,380.54,-1178.24,300.3,-1105.56,209.46,-982.94,271.54,-883,197.34,-802.12,479.28,-888.32,473.62,-924.64,423.7,-1007.44,432.78,-720.44,511.04,-685.26,439.58,-554.8,438.44,-768.08,411.22,-717.02,310.26,625.62,486.26],"hull":17,"edges":[18,20,18,34,34,36,36,6,12,14,2,0,0,32,0,74,74,76,76,36,30,32,24,168,168,34,24,26,26,132,132,134,134,136,136,138,138,74,170,186,186,184,184,180,180,178,178,176,176,172,172,174,174,170,188,190,190,192,192,196,196,198,198,200,200,212,212,208,208,206,206,204,204,202,202,188,20,22,22,24,26,28,28,30,2,4,4,6,6,8,8,10,10,12,14,16,16,18],"width":1568,"height":621}},"smoke_2.2":{"Effects_02":{"type":"mesh","uvs":[1,0.49346,1,1,0.61945,1,0.42654,1,0.34442,1,0.19098,1,0.08489,1,0,1,0,0.66316,0,0.45896,0,0,0.1888,0,0.32733,0,0.58916,0,0.6957,0,0.83771,0,1,0,0.22411,0.47167,0.39935,0.70307,0.09739,0.9081,0.17496,0.86472,0.14372,0.8989,0.16663,0.76744,0.19475,0.71354,0.20516,0.63729,0.21766,0.8358,0.26121,0.79636,0.31083,0.84128,0.28951,0.87524,0.33116,0.88181,0.32856,0.9436,0.07812,0.79636,0.04792,0.79767,0.04272,0.66621,0.02085,0.61363,0.05261,0.55315,0.05469,0.49925,0.83565,0.47107,0.65901,0.63639,0.52192,0.88954,0.55603,0.8706,0.54375,0.91709,0.59422,0.90159,0.62968,0.81549,0.67061,0.80516,0.71835,0.87404,0.69754,0.76077,0.74763,0.70788,0.79363,0.76767,0.83826,0.71247,0.85283,0.79182,0.89974,0.78837,0.94063,0.75797,0.94018,0.69013,0.96113,0.65333,0.98162,0.66138,0.85684,0.61194,0.84727,0.54064,0.7949,0.19021,0.76712,0.14997,0.73889,0.14307,0.7357,0.08212,0.70701,0.09707,0.69016,0.02808,0.67103,0.04303,0.66511,0.09592,0.59225,0.08672,0.59452,0.25806,0.68788,0.29945,0.76485,0.342,0.91103,0.14997,0.89874,0.28795,0.88097,0.41674,0.8154,0.3397,0.83134,0.22241,0.80356,0.12352,0.80993,0.02578,0.85957,0.06948,0.82633,0.09362,0.85411,0.13732,0.87141,0.20516,0.85547,0.2868,0.86595,0.35464,0.83589,0.04878,0.31267,0.31712,0.45987,0.41274,0.39814,0.26461,0.43542,0.31707,0.38837,0.17202,0.39142,0.08407,0.44215,0.10876,0.43176,0.20597,0.47026,0.24918,0.48065,0.36799,0.02323,0.08149,0.08599,0.07052,0.11351,0.13147,0.10627,0.18511,0.14489,0.14975,0.1642,0.19242,0.20476,0.25825,0.01792,0.15585,0.0633,0.1461,0.07199,0.21071,0.09516,0.28385,0.13427,0.23387,0.16613,0.2936,0.19193,0.0666,0.16444,0.07117,0.15286,0.11135,0.12645,0.10405,0.21797,0.04102,0.22919,0.09857,0.27079,0.09948,0.20278,0.1214,0.21906,0.20269,0.64461,0.09974],"triangles":[76,14,15,14,64,13,111,11,12,63,64,14,83,76,15,107,11,111,77,15,16,83,15,77,95,10,11,108,95,11,107,108,11,94,10,95,61,14,76,62,63,14,90,89,12,116,66,13,13,90,12,78,76,83,13,64,116,61,62,14,113,112,111,12,113,111,65,116,64,110,95,108,66,90,13,109,110,108,114,107,111,114,111,112,76,59,61,75,76,78,96,95,110,77,78,83,79,78,77,59,60,61,62,61,60,102,94,95,102,95,96,98,110,109,96,110,98,76,75,59,70,77,16,79,77,70,101,10,94,101,94,102,88,12,89,88,89,90,97,102,96,58,59,75,114,99,109,98,109,99,108,107,114,114,109,108,115,114,112,99,114,115,80,79,70,91,88,90,103,102,97,74,78,79,74,79,80,75,78,74,58,75,74,98,97,96,105,98,99,105,97,98,92,90,66,91,90,92,67,66,116,92,66,67,100,99,115,86,88,91,104,103,97,104,97,105,81,74,80,71,80,70,81,80,71,106,99,100,105,99,106,104,105,106,64,62,65,62,64,63,68,62,60,68,65,62,116,65,68,67,116,68,87,91,92,86,91,87,12,88,84,12,84,113,84,88,86,73,58,74,73,74,81,69,60,59,69,59,58,69,58,73,68,60,69,82,81,71,73,81,82,93,92,67,87,92,93,85,87,93,72,82,71,9,10,101,37,73,82,37,82,72,69,73,37,100,115,84,17,100,84,106,100,17,113,115,112,84,115,113,104,106,17,101,102,103,9,101,103,9,103,104,9,104,17,70,16,0,71,70,0,72,71,0,37,72,0,36,9,17,57,37,0,35,9,36,54,56,57,34,9,35,38,67,68,38,68,69,38,69,37,24,36,17,35,36,24,0,54,57,55,54,0,8,9,34,33,34,35,53,56,54,18,86,87,18,87,85,84,86,18,17,84,18,26,24,17,38,18,85,93,38,85,38,93,67,47,38,37,47,37,57,49,47,57,56,49,57,24,22,35,35,31,33,52,53,54,46,38,47,24,23,22,48,47,49,51,56,53,51,53,52,49,56,51,50,49,51,48,49,50,18,26,17,23,24,26,22,31,35,32,33,31,44,38,46,38,40,18,43,38,44,25,23,26,22,23,25,27,26,18,20,22,25,43,40,38,45,46,47,45,47,48,44,46,45,28,26,27,29,27,18,39,18,40,21,31,22,21,22,20,42,40,43,19,31,21,41,39,40,29,28,27,30,28,29,8,32,7,33,8,34,32,8,33,19,32,31,6,32,19,7,32,6,5,20,25,21,20,5,6,19,21,5,6,21,3,4,29,18,3,29,30,29,4,5,28,30,25,26,28,5,25,28,4,5,30,39,3,18,2,42,43,41,40,42,2,41,42,3,39,41,3,41,2,55,0,1,52,54,55,1,52,55,51,52,1,50,51,1,45,48,50,1,45,50,2,43,44,45,2,44,2,45,1],"vertices":[1732,-50.88,1732,-680,538.6,-680,-66.38,-680,-323.9,-680,-805.08,-680,-1137.78,-680,-1404,-680,-1404,-261.64,-1404,-8.02,-1404,562,-811.94,562,-377.48,562,443.6,562,777.72,562,1223.06,562,1732,562,-701.18,-23.82,-151.64,-311.22,-1098.6,-565.86,-855.32,-511.98,-953.28,-554.44,-881.44,-391.16,-793.28,-324.22,-760.62,-229.52,-721.42,-476.06,-584.84,-427.08,-429.24,-482.86,-496.1,-525.04,-365.48,-533.2,-373.64,-609.94,-1159.02,-427.08,-1253.72,-428.72,-1270.04,-265.44,-1338.62,-200.12,-1239.02,-125.02,-1232.48,-58.08,1216.62,-23.08,662.66,-228.4,232.76,-542.8,339.7,-519.28,301.22,-577.02,459.46,-557.78,570.68,-450.84,699.02,-438,848.74,-523.56,783.48,-382.88,940.58,-317.18,1084.82,-391.44,1224.78,-322.9,1270.48,-421.44,1417.58,-417.16,1545.82,-379.4,1544.4,-295.14,1610.1,-249.44,1674.36,-259.44,1283.04,-198.02,1253.06,-109.48,1088.82,325.76,1001.7,375.74,913.16,384.32,903.16,460,813.18,441.44,760.34,527.12,700.36,508.56,681.8,442.86,453.28,454.28,460.44,241.5,753.2,190.08,994.56,137.24,1453,375.74,1414.44,204.36,1358.74,44.42,1153.08,140.1,1203.06,285.76,1115.96,408.58,1135.94,529.98,1291.62,475.72,1187.36,445.72,1274.48,391.46,1328.74,307.2,1278.76,205.8,1311.6,121.54,1217.34,501.42,-423.46,168.14,38.14,49.38,-155.42,233.36,-38.52,168.2,-186.08,348.34,-176.5,457.58,-17.44,426.92,-50.02,306.18,70.72,252.52,103.3,104.96,-1331.16,460.8,-1134.34,474.42,-1048.04,398.72,-1070.74,332.1,-949.62,376,-889.06,323.02,-761.88,241.26,-1347.82,368.44,-1205.5,380.54,-1178.24,300.3,-1105.56,209.46,-982.94,271.54,-883,197.34,-802.12,479.28,-888.32,473.62,-924.64,423.7,-1007.44,432.78,-720.44,511.04,-685.26,439.58,-554.8,438.44,-768.08,411.22,-717.02,310.26,625.62,486.26],"hull":17,"edges":[18,20,18,34,34,36,36,6,12,14,2,0,0,32,0,74,74,76,76,36,30,32,24,168,168,34,24,26,26,132,132,134,134,136,136,138,138,74,170,186,186,184,184,180,180,178,178,176,176,172,172,174,174,170,188,190,190,192,192,196,196,198,198,200,200,212,212,208,208,206,206,204,204,202,202,188,20,22,22,24,26,28,28,30,2,4,4,6,6,8,8,10,10,12,14,16,16,18],"width":1568,"height":621}},"Star_BG":{"Star_BG":{"type":"mesh","uvs":[1,1,0,1,0,0,1,0],"triangles":[1,2,3,1,3,0],"vertices":[1304,-868,-1270,-868,-1270,446,1304,446],"hull":4,"edges":[0,2,2,4,4,6,0,6],"width":1287,"height":657}},"Star_Glow":{"Star_Glow":{"type":"mesh","uvs":[1,1,0,1,0,0,1,0],"triangles":[1,2,3,1,3,0],"vertices":[1220,-354,-1222,-354,-1222,352,1220,352],"hull":4,"edges":[0,2,2,4,4,6,0,6],"width":1221,"height":353}},"star_glow":{"star_glow":{"type":"clipping","end":"Star_Glow","vertexCount":4,"vertices":[-349.86,848.1,715.2,-312.04,273.5,-770.12,-811.62,402.68],"color":"ce3a3aff"}},"Win":{"Win":{"type":"mesh","uvs":[1,1,0,1,0,0,1,0],"triangles":[1,2,3,1,3,0],"vertices":[1050.08,-343,-21.92,-343,-21.92,249,1050.08,249],"hull":4,"edges":[0,2,2,4,4,6,0,6],"width":536,"height":296}},"win_glow":{"Layer 143 copy 2":{"type":"mesh","uvs":[1,1,0.51046,0.99998,0.51078,1.0E-5,1,0],"triangles":[2,3,0,1,2,0],"vertices":[1,4,1020.08,-277,1,1,4,-23.62,-277,1,1,4,-22.94,274.98,1,1,4,1020.08,275,1],"hull":4,"edges":[0,6,4,6,0,2,2,4],"width":1066,"height":276}},"Win_Shadow":{"Win_Shadow":{"type":"mesh","uvs":[1,1,0,1,0,0,1,0],"triangles":[1,2,3,1,3,0],"vertices":[1024.08,-295,-13.92,-295,-13.92,247,1024.08,247],"hull":4,"edges":[0,2,2,4,4,6,0,6],"width":519,"height":271}}}}],"animations":{"appear":{"slots":{"Bulb_on_01_Buttom":{"attachment":[{"time":0.2667},{"time":0.4,"name":"Bulb_on_01_Buttom"},{"time":0.5333},{"time":0.6667,"name":"Bulb_on_01_Buttom"},{"time":0.8},{"time":0.9333,"name":"Bulb_on_01_Buttom"},{"time":1.0667},{"time":1.2,"name":"Bulb_on_01_Buttom"},{"time":1.3333},{"time":1.4667,"name":"Bulb_on_01_Buttom"}]},"Bulb_on_01_L":{"attachment":[{"time":0.2667},{"time":0.4,"name":"Bulb_on_01_L"},{"time":0.5333},{"time":0.6667,"name":"Bulb_on_01_L"},{"time":0.8},{"time":0.9333,"name":"Bulb_on_01_L"},{"time":1.0667},{"time":1.2,"name":"Bulb_on_01_L"},{"time":1.3333},{"time":1.4667,"name":"Bulb_on_01_L"}]},"Bulb_on_01_R":{"attachment":[{"time":0.2667},{"time":0.4,"name":"Bulb_on_01_R"},{"time":0.5333},{"time":0.6667,"name":"Bulb_on_01_R"},{"time":0.8},{"time":0.9333,"name":"Bulb_on_01_R"},{"time":1.0667},{"time":1.2,"name":"Bulb_on_01_R"},{"time":1.3333},{"time":1.4667,"name":"Bulb_on_01_R"}]},"Bulb_on_01_Top":{"attachment":[{"time":0.2667},{"time":0.4,"name":"Bulb_on_01_Top"},{"time":0.5333},{"time":0.6667,"name":"Bulb_on_01_Top"},{"time":0.8},{"time":0.9333,"name":"Bulb_on_01_Top"},{"time":1.0667},{"time":1.2,"name":"Bulb_on_01_Top"},{"time":1.3333},{"time":1.4667,"name":"Bulb_on_01_Top"}]},"Bulb_on_02_Bottom":{"attachment":[{"time":0.1333},{"time":0.2667,"name":"Bulb_on_02_Bottom"},{"time":0.4},{"time":0.5333,"name":"Bulb_on_02_Bottom"},{"time":0.6667},{"time":0.8,"name":"Bulb_on_02_Bottom"},{"time":0.9333},{"time":1.0667,"name":"Bulb_on_02_Bottom"},{"time":1.2},{"time":1.3333,"name":"Bulb_on_02_Bottom"},{"time":1.4667},{"time":1.5,"name":"Bulb_on_02_Bottom"}]},"Bulb_on_02_L":{"attachment":[{"time":0.1333},{"time":0.2667,"name":"Bulb_on_02_L"},{"time":0.4},{"time":0.5333,"name":"Bulb_on_02_L"},{"time":0.6667},{"time":0.8,"name":"Bulb_on_02_L"},{"time":0.9333},{"time":1.0667,"name":"Bulb_on_02_L"},{"time":1.2},{"time":1.3333,"name":"Bulb_on_02_L"},{"time":1.4667},{"time":1.5,"name":"Bulb_on_02_L"}]},"Bulb_on_02_R":{"attachment":[{"time":0.1333},{"time":0.2667,"name":"Bulb_on_02_R"},{"time":0.4},{"time":0.5333,"name":"Bulb_on_02_R"},{"time":0.6667},{"time":0.8,"name":"Bulb_on_02_R"},{"time":0.9333},{"time":1.0667,"name":"Bulb_on_02_R"},{"time":1.2},{"time":1.3333,"name":"Bulb_on_02_R"},{"time":1.4667},{"time":1.5,"name":"Bulb_on_02_R"}]},"Bulb_on_02_Top":{"attachment":[{"time":0.1333},{"time":0.2667,"name":"Bulb_on_02_Top"},{"time":0.4},{"time":0.5333,"name":"Bulb_on_02_Top"},{"time":0.6667},{"time":0.8,"name":"Bulb_on_02_Top"},{"time":0.9333},{"time":1.0667,"name":"Bulb_on_02_Top"},{"time":1.2},{"time":1.3333,"name":"Bulb_on_02_Top"},{"time":1.4667},{"time":1.5,"name":"Bulb_on_02_Top"}]},"Effects_01":{"rgba":[{"color":"ffffff00","curve":"stepped"},{"time":0.3,"color":"ffffff00"},{"time":0.5667,"color":"ffffffff"}]},"epic_glow":{"rgba":[{"color":"ffffff00","curve":"stepped"},{"time":0.2667,"color":"ffffff00"},{"time":0.7,"color":"ffffffff","curve":"stepped"},{"time":0.7667,"color":"ffffffff"},{"time":1.1333,"color":"ffffff00"}],"attachment":[{"time":1.5}]},"green smoke1":{"rgba":[{"color":"ffffff00","curve":"stepped"},{"time":0.3,"color":"ffffff00"},{"time":0.5667,"color":"ffffffff"}]},"green smoke2":{"rgba":[{"color":"ffffff00"}]},"smoke_2":{"rgba":[{"color":"ffffff00","curve":"stepped"},{"time":0.3,"color":"ffffff00"},{"time":0.5667,"color":"ffffffff"}]},"smoke_2.2":{"rgba":[{"time":0.3,"color":"ffffffff"},{"time":0.5667,"color":"ffffff00"}]},"win_glow":{"rgba":[{"color":"ffffff00","curve":"stepped"},{"time":0.4,"color":"ffffff00"},{"time":0.8,"color":"ffffffff","curve":"stepped"},{"time":0.8667,"color":"ffffffff"},{"time":1.2333,"color":"ffffff00"}],"attachment":[{"time":1.5}]}},"bones":{"main":{"scale":[{"x":0,"y":0,"curve":[0.109,-0.098,0.224,1.341,0.109,-0.098,0.224,1.341]},{"time":0.3333,"x":1.502,"y":1.502,"curve":"stepped"},{"time":1.1333,"x":1.502,"y":1.502,"curve":[1.184,1.577,1.244,1,1.184,1.577,1.244,1]},{"time":1.3}]},"glows":{"scale":[{"x":0,"y":0,"curve":"stepped"},{"time":0.1333,"x":0,"y":0,"curve":[0.244,0,0.356,1.451,0.244,0,0.356,1.451]},{"time":0.4667,"x":1.502,"y":1.502,"curve":[0.582,1.554,1.018,1.523,0.582,1.554,1.018,1.523]},{"time":1.1333,"x":1.502,"y":1.502,"curve":[1.189,1.492,1.244,1,1.189,1.492,1.244,1]},{"time":1.3}]},"epic":{"scale":[{"x":0,"y":0,"curve":"stepped"},{"time":0.1667,"x":0,"y":0,"curve":[0.256,0,0.345,1.498,0.256,0,0.345,1.603]},{"time":0.4333,"x":1.7,"y":1.7,"curve":[0.561,1.994,0.978,1.924,0.557,1.835,0.977,1.7]},{"time":1.1,"x":1.8,"y":1.7,"curve":[1.155,1.744,1.211,1.065,1.156,1.7,1.211,1.065]},{"time":1.2667,"x":0.96,"y":0.96,"curve":[1.322,0.854,1.378,1,1.322,0.854,1.378,1]},{"time":1.4333}]},"win":{"scale":[{"x":0,"y":0,"curve":"stepped"},{"time":0.3333,"x":0,"y":0,"curve":[0.411,0,0.489,1.546,0.411,0,0.489,1.656]},{"time":0.5667,"x":1.7,"y":1.7,"curve":[0.677,1.919,1.085,1.899,0.685,1.767,1.083,1.7]},{"time":1.2,"x":1.8,"y":1.7,"curve":[1.261,1.748,1.306,1.077,1.261,1.7,1.306,1.077]},{"time":1.3667,"x":0.96,"y":0.96,"curve":[1.413,0.87,1.456,1,1.413,0.87,1.456,1]},{"time":1.5}]},"epic_win":{"scale":[{"time":0.1333,"curve":[0.311,1,0.489,1.05,0.311,1,0.489,1.05]},{"time":0.6667,"x":1.05,"y":1.05,"curve":[0.8,1.05,0.933,1,0.8,1.05,0.933,1]},{"time":1.0667}]},"star_mask":{"rotate":[{"time":1.5,"value":17.61}],"translate":[{"time":1.5,"x":373.26,"y":9.84}]}},"attachments":{"default":{"green smoke1":{"green smoke":{"deform":[{"vertices":[61.01355,20.33789,16.87903,37.50897,73.79026,100.61981,17.01257,76.93616,31.92493,49.88586,0,0,40.15137,81.73669,51.62317,114.71814,58.79297,47.32117,121.88806,45.88726,101.79224,19.08606,114.51648,-97.55109,103.12732,-120.4856,34.62097,-60.33936,54.4043,-49.45844,18.79428,-76.16608,8.9025,-74.18774,70.56306,-104.83661,23.185,-29.23334,48.38611,-73.58716,-25.17273,-103.45935,-99.8606,-98.5564,-197.9674,-96.92581,-284.93982,20.51944,-101.81226,40.15134,-162.1123,51.01715,-128.82312,74.20038,-6.46533,94.76892,47.26697,37.80835,-86.58594,-26.56451,-47.25647,-14.98376,0,0,26.50977,10.37336,0,0,54.02028,-103.27399,30.50687,-64.92789,-68.10773,-12.17865,50.84247,-66.7308,20.07562,37.28345,22.9436,30.11349,7.16992,17.20776,-15.77368,67.39687,0,0,-28.67957,-63.09503,45.88745,28.6795,34.99109,68.92197,34.99304,57.77933,81.646,-45.59454,191.00513,-73.32568,40.91003,-77.06183,48.75146,-5.40192,-16.27588,-34.9931,1.97833,-45.50183,-32.6427,-46.49097,66.27438,37.5885,-15.70362,3.93121,22.24362,34.95422,25.45504,31.51343,54.77475,55.79584,-5.19446,-4.76691,7.05634,-14.11261,-28.02271,-35.61029,9.48004,-36.57123,-15.12067,15.12067,47.37805,-21.16895,40.32178,-13.10461,0,0,4.22217,-52.07388,-4.48804,-75.41611,31.38806,-35.47742,51.04211,-123.66409,-63.28101,-53.72043,-74.91882,21.89938,-25.52515,-18.53485,-118.71301,71.03427,34.95424,-54.02011,47.66486,-65.142],"curve":[0.1,0,0.2,1]},{"time":0.3,"curve":[0.515,0,1.052,1]},{"time":1.2667,"vertices":[108.46857,36.15625,30.00717,66.68262,131.18268,178.87964,30.24454,136.77539,56.75543,88.68591,0,0,71.38013,145.30963,91.77466,203.9433,104.52087,84.12656,216.68982,81.57733,180.96399,33.93076,203.58484,-173.42407,183.3374,-214.1966,61.54846,-107.26996,96.71869,-87.92615,33.41205,-135.40637,15.82666,-131.88928,125.44542,-186.3761,41.21777,-51.97034,86.01965,-130.8216,-44.75146,-183.92761,-177.52979,-175.21136,-351.94214,-172.31247,-506.55994,36.479,-180.99963,71.38013,-288.1996,90.69714,-229.0188,131.91174,-11.4939,168.47803,84.03015,67.21478,-153.93042,-47.22577,-84.01147,-26.6378,0,0,47.12842,18.44152,0,0,96.03602,-183.5982,54.23441,-115.42734,-121.08038,-21.65088,90.38657,-118.63251,35.69006,66.28162,40.78857,53.53508,12.74658,30.59155,-28.04224,119.81665,0,0,-50.98584,-112.16891,81.57764,50.98576,62.2063,122.52789,62.20996,102.71875,145.14832,-81.05695,339.56458,-130.35675,72.729,-136.99872,86.66919,-9.60333,-28.93494,-62.20996,3.51703,-80.89209,-58.03143,-82.65057,117.82114,66.82404,-27.91754,6.98883,39.54419,62.14087,45.25342,56.0239,97.37732,99.19263,-9.23458,-8.47449,12.54456,-25.08905,-49.81812,-63.30713,16.85333,-65.0155,-26.88116,26.8812,84.2276,-37.63367,71.68317,-23.29706,0,0,7.5061,-92.57578,-7.97864,-134.07309,55.8009,-63.07092,90.74146,-219.84726,-112.49951,-95.50296,-133.18896,38.93221,-45.37799,-32.95087,-211.04529,126.28317,62.14087,-96.03571,84.73749,-115.80798],"curve":[1.344,0,1.422,1]},{"time":1.5,"offset":22,"vertices":[83.00403,-3.68909,90.3822,-51.64703,0,0,0,0,0,0,0,0,0,0,0,0,0,0,0,0,0,0,0,0,0,0,0,0,0,0,0,0,0,0,0,0,0,0,0,0,0,0,0,0,0,0,0,0,0,0,0,0,0,0,0,0,0,0,0,0,0,0,0,0,0,0,0,0,0,0,29.51257,1.8446,116.20569,-18.44543,130.96191,-23.97906,60.86963,-22.13446,53.49146,3.68909]}]}},"green smoke2":{"green smoke":{"deform":[{"vertices":[10.71875,-125.56305,34.66418,-141.1817,13.425,-112.24847,28.09497,-98.69073,35.21887,-107.95361,15.59607,-185.76129,-9.95325,-94.93793,-30.56238,-85.5744,-51.08618,-16.40939,-91.87537,-3.0625,-18.375,84.98477,0.76563,91.87543,0,0,0,0,13.44745,55.01208,4.89005,51.3446,14.66998,55.01208,22.0048,51.34467,28.11731,29.33978,19.55981,41.5647,-6.11243,57.45709,24.44995,70.90436,0,0,36.6748,4.88998,56.23462,1.22253,102.25757,-62.58319,86.73682,-89.5282,54.35962,-118.67242,15.31256,-119.43811,8.5575,-55.01215,120.23853,-3.9511,0,0,26.89478,23.22736,0,0,11.00244,-64.79202,44.82571,-70.7439,36.75012,-84.21912,-3.6424,-104.75287,-19.09045,-110.28552,-119.2998,-2.69366,-8.44434,-37.72668,-68.45947,7.33498,-98.87354,30.24104,-64.79199,-18.33738,0,0,-8.422,36.75015,11.00244,57.45709,41.56482,67.237,26.8949,79.46191,8.5575,51.34467,18.33716,48.89966,24.44995,56.23462,11.00256,36.67474,34.22974,67.23706,45.23221,45.23218,18.33738,55.01215,20.78233,59.90204,17.1149,47.67719,3.66757,42.78723,20.78234,25.67236,34.22974,24.44983,13.44751,74.57202,23.22736,77.01709,0,0,20.78241,25.6723,15.89246,41.56473,12.22501,51.3446,-2.44495,48.89957,6.11243,42.78714,12.22485,59.9021,29.33997,36.67474,15.89246,77.01697,28.11731,18.33736,56.65637,-73.50031,51.59326,-91.1825,21.52283,-104.29593,42.3429,-145.77542],"curve":[0.078,0,0.156,1]},{"time":0.2333,"curve":[0.446,0,0.954,1]},{"time":1.1667,"vertices":[26.03119,-304.93884,84.18448,-342.8698,32.60356,-272.60345,68.23059,-239.67752,85.53149,-262.17303,37.87622,-451.13452,-24.17224,-230.56348,-74.2229,-207.82355,-124.06641,-39.85138,-223.12598,-7.4375,-44.62512,206.39159,1.85938,223.126,0,0,0,0,32.65808,133.60077,11.87585,124.69409,35.62711,133.60083,53.44024,124.69415,68.28491,71.25378,47.50244,100.94281,-14.84436,139.5387,59.37842,172.19635,0,0,89.06738,11.87568,136.56982,2.96899,248.33972,-151.9877,210.6466,-217.4256,132.01611,-288.2044,37.18768,-290.0639,20.78247,-133.6009,292.00793,-9.59552,0,0,65.31592,56.4093,0,0,26.7202,-157.35205,108.86243,-171.80658,89.25031,-204.5321,-8.84576,-254.39973,-46.36261,-267.83624,-289.72803,-6.54176,-20.50757,-91.62195,-166.25879,17.8135,-240.12158,73.44255,-157.35205,-44.53365,0,0,-20.45349,89.25038,26.72009,139.53867,100.94312,163.28989,65.31604,192.97894,20.78235,124.69415,44.5332,118.75626,59.3783,136.56973,26.72046,89.06726,83.12933,163.28995,109.84967,109.84955,44.53364,133.60095,50.47137,145.47638,41.56478,115.78741,8.90695,103.91174,50.47138,62.34714,83.12933,59.37811,32.6582,181.10352,56.40924,187.04144,0,0,50.47156,62.34705,38.59595,100.94293,29.68927,124.69409,-5.93762,118.75607,14.84448,103.91162,29.68896,145.4765,71.25415,89.0672,38.59607,187.04121,68.28491,44.5336,137.59412,-178.5007,125.29779,-221.44318,52.2697,-253.29005,102.8327,-354.026]}]}},"smoke_2":{"Effects_02":{"deform":[{"offset":4,"vertices":[29.87561,-24.37048,18.92764,-29.44287,43.11267,-47.31879,49.422,-91.48322,0,0,0,0,-72.43433,-1.74542,-70.65002,29.01698,0,0,-41.63336,191.86377,0,0,0,0,-22.58087,50.20801,12.08728,92.97797,0,0,0,0,0,0,0,0,8.15674,-48.99026,-10.16168,-17.55194,21.24719,5.54266,0,0,0,0,37.30518,-94.96313,13.48303,-47.30942,17.55188,-10.16165,-24.01846,-35.10394,14.72147,-22.08209,18.91821,-38.51404,68.604,-52.24545,-1.63281,-47.27597,-23.16406,-29.03094,-74.22083,-4.88895,-38.64355,29.82316,-55.64465,87.24324,0,0,0,0,10.16811,25.10828,49.23761,-7.31201,24.97687,-41.12512,38.20273,-25.91364,41.01489,-16.09946,16.81171,-11.21521,25.45959,-21.38599,0,0,36.36896,18.97516,-26.88159,-63.25043,-12.65002,-42.69394,3.16235,-91.71301,12.65027,-39.53143,28.46252,-23.71893,31.625,33.20651,36.3689,-4.74384,25.30017,52.18155,37.9502,9.48758,33.20642,20.5564,35.03674,53.97559,35.0368,53.97559,35.0368,53.97559,-4.32318,33.74487,-2.41394,63.94208,-28.21869,54.09326,-35.93933,48.12354,-24.84631,37.79901,0,0,0,0,0,0,0,0,55.34412,69.57541,134.29944,45.11006,115.2926,-40.9103,23.24451,-40.91032,0,0,0,0,-24.17432,38.12097,40.91028,48.3486,-10.22754,-47.41882,19.52539,-39.98053,48.34851,-22.31473,43.69983,-12.08716,99.48633,-26.03384,13.94666,21.38492,31.44315,51.65675,0,0,0,0,0,0,27.00496,35.38586,0,45.62909,77.29008,111.74484,75.42782,35.38589,73.56543,7.44969,55.87242,-72.63418,-107.48755,26.24033,-58.47864,65.59097,-56.53552,46.70267,-74.245,-9.56082,-63.97168,34.13037,-31.61011,-58.52414,4.92944,-43.85918,-102.77185,0.48587,-90.27026,-55.117,-61.43896,-48.87909,-53.72424,-86.14414,-30.94946,-99.25461,-0.33026,-79.01246,93.7887,84.55502,17.59344,145.36298,39.92773,66.87979,9.98151,125.39993,140.78851,63.71848,50.28491,-19.17429,75.61429,0.33237,-28.20013,16.22031,87.55127,-30.36264,-33.26025,-19.27228],"curve":[0.111,0,0.222,1]},{"time":0.3333,"curve":[0.545,0,1.088,1]},{"time":1.3,"offset":4,"vertices":[47.80103,-38.99274,30.28422,-47.10858,68.9803,-75.71008,79.0752,-146.37317,0,0,0,0,-115.89502,-2.79266,-113.04004,46.42716,0,0,-66.6134,306.982,0,0,0,0,-36.12939,80.33276,19.3396,148.76477,0,0,0,0,0,0,0,0,13.05078,-78.38449,-16.25867,-28.08313,33.99548,8.86826,0,0,0,0,59.68829,-151.94104,21.57288,-75.69507,28.08301,-16.25864,-38.42953,-56.16626,23.55432,-35.33136,30.2691,-61.62244,109.76636,-83.59274,-2.61255,-75.64154,-37.0625,-46.44952,-118.75342,-7.8223,-61.82971,47.71704,-89.03137,139.58919,0,0,0,0,16.26897,40.17328,78.78018,-11.69922,39.96298,-65.80017,61.12436,-41.46179,65.62384,-25.75912,26.89874,-17.94431,40.73535,-34.21759,0,0,58.19031,30.36026,-43.0105,-101.20068,-20.23999,-68.3103,5.05981,-146.74084,20.24048,-63.25031,45.54004,-37.95026,50.6001,53.1304,58.19031,-7.59015,40.48022,83.49048,60.72034,15.18011,53.13037,32.89022,56.05884,86.36093,56.0589,86.36093,56.05884,86.36093,-6.91705,53.99176,-3.8623,102.30731,-45.14984,86.54919,-57.50299,76.99768,-39.75415,60.47839,0,0,0,0,0,0,0,0,88.55066,111.32068,214.87915,72.1761,184.46814,-65.45648,37.19128,-65.45652,0,0,0,0,-38.67883,60.99353,65.45654,77.3577,-16.36414,-75.87012,31.2406,-63.96887,77.35767,-35.70355,69.9198,-19.33946,159.17822,-41.65414,22.3147,34.21591,50.30902,82.65082,0,0,0,0,0,0,43.20793,56.61737,0,73.00656,123.66412,178.79166,120.68448,56.61743,117.70468,11.91951,89.39589,-116.21468,-171.97998,41.98453,-93.56592,104.94553,-90.45691,74.72424,-118.79199,-15.2973,-102.35474,54.60861,-50.57617,-93.63861,7.88715,-70.17468,-164.43494,0.7774,-144.43237,-88.18719,-98.30237,-78.20651,-85.95886,-137.83063,-49.5191,-158.80737,-0.52844,-126.41992,150.06189,135.288,28.14954,232.58075,63.8844,107.00763,15.9704,200.63986,225.2616,101.94949,80.45581,-30.67883,120.98285,0.5318,-45.12024,25.95251,140.08197,-48.58023,-53.21643,-30.83566],"curve":[1.367,0,1.433,1]},{"time":1.5}]}},"smoke_2.2":{"Effects_02":{"deform":[{"offset":2,"vertices":[-3.41077,9.25787,0.24359,4.14172,2.6799,4.75073,4.98871,4.74188,0,0,0,0,3.16711,6.69977,4.0199,-0.12183,5.15808,1.13844,0,0,-2.09052,-2.36029,-1.55103,-5.3949,0.51999,-1.11426,-2.59998,-3.93707,1.1886,-3.63995,0,0,-0.32129,-3.19544,0,0,3.88428,7.47491,1.49365,5.64771,1.18378,5.2373,-0.77832,2.11261,-1.9458,1.50107,-3.4469,0.16678,-0.13983,5.54465,0.12183,5.12363,0.74399,7.38745,1.88528,7.04327,1.42743,7.29749,0.84851,5.49402,3.22449,5.67068,3.34705,5.65585,6.34912,1.41681,6.12927,0.99329,4.78442,-2.18698,8.80566,-0.95932,0,0,0,0,0,4.38531,-0.24362,5.84711,0.36545,5.84711,0.24365,4.75073,0.7309,3.89807,0.85272,3.65445,0,0,0,0,0,0,0,0,0,0,0.36548,4.99438,-0.48718,5.35983,-0.4873,5.72528,0.97449,4.99438,-0.60913,4.38531,-3.41077,1.21814,0,0,0,0,-1.63428,-1.18857,0.74286,-3.04568,0.14856,-2.67426,0,0,0.5943,-2.07999,2.5257,-3.26849,0.29712,-2.45139,0,-4.01987,0,0,0,0,0,0,0,0,0,0,-1.33997,-2.19266,-8.16162,-3.16718,0,0,-3.86279,-0.9657,0,0,0,0,-0.14856,-2.89709,-1.85718,-2.00571,-4.25781,-3.96951,-1.94897,-1.58359,-4.14172,1.5836,-2.92358,-0.24364,-0.89148,-2.37711,0,0,0,0,3.709,-2.36028,0,0,2.56258,-3.37183,0,0,0.13488,-2.83231,1.95566,-4.11362,0.60692,-1.68591,-2.09052,-0.13488,3.20703,-5.59662,-2.24902,-5.67029,-0.33716,-3.16953,1.07898,-2.69745,-0.47205,-1.34875,0,0,0,0,1.85266,-5.01035,-0.8092,-3.64157,1.68591,-1.48361,3.16956,-1.07898,1.8208,-2.29285,0,0,-0.4046,-2.63,1.01154,-2.49515,0,0,0,0,1.34875,-2.49515,1.01154,-2.36029,-0.87665,-1.95566,-1.01154,-2.29285,0,0,-2.15424,-3.34283],"curve":[0.011,0,0.022,1]},{"time":0.0333,"curve":[0.211,0,0.389,1]},{"time":0.5667,"offset":2,"vertices":[-57.98352,157.38373,4.1416,70.40857,45.55834,80.7627,84.80777,80.61163,0,0,0,0,53.84167,113.896,68.33752,-2.07077,87.68628,19.35338,0,0,-35.53882,-40.12451,-26.36761,-91.71313,8.83984,-18.94263,-44.19934,-66.93033,20.20544,-61.87888,0,0,-5.46155,-54.32252,0,0,66.03174,127.07318,25.39191,96.01056,20.12451,89.03354,-13.23157,35.91425,-33.07898,25.51794,-58.5968,2.83537,-2.37762,94.25897,2.0708,87.10123,12.64758,125.58621,32.0498,119.73492,24.2662,124.05728,14.42432,93.39783,54.81653,96.40128,56.89978,96.14917,107.93579,24.08553,104.19739,16.88576,81.33411,-37.17847,149.69666,-16.30824,0,0,0,0,0,74.55011,-4.14163,99.40024,6.21268,99.40024,4.14185,80.7627,12.4248,66.26685,14.49591,62.12515,0,0,0,0,0,0,0,0,0,0,6.2124,84.90436,-8.2832,91.11685,-8.28345,97.32944,16.56665,84.90427,-10.35437,74.55023,-57.98352,20.70844,0,0,0,0,-27.78235,-20.20535,12.6283,-51.77631,2.52563,-45.46216,0,0,10.10266,-35.35944,42.93652,-55.56479,5.05127,-41.67358,0,-68.33777,0,0,0,0,0,0,0,0,0,0,-22.77917,-37.27509,-138.74622,-53.8418,0,0,-65.66748,-16.4169,0,0,0,0,-2.52563,-49.25064,-31.57092,-34.09665,-72.38318,-67.48157,-33.13342,-26.9209,-70.40869,26.92102,-49.70032,-4.14172,-15.15405,-40.41074,0,0,0,0,63.05278,-40.12453,0,0,43.56378,-57.32074,0,0,2.29282,-48.14941,33.24604,-69.93134,10.31778,-28.66045,-35.53888,-2.2928,54.51953,-95.1424,-38.23437,-96.39444,-5.73206,-53.88156,18.34265,-45.8566,-8.02502,-22.92838,0,0,0,0,31.49561,-85.1759,-13.75684,-61.90646,28.66028,-25.22113,53.88147,-18.34262,30.95325,-38.97815,0,0,-6.87854,-44.71021,17.19617,-42.41739,0,0,0,0,22.92834,-42.41736,17.19629,-40.1246,-14.90332,-33.24603,-17.19629,-38.97815,0,0,-36.62231,-56.82767]}]}},"star_glow":{"star_glow":{"deform":[{"time":1.5,"vertices":[591.19495,109.38898,-404.13788,-343.01678,-522.60376,-76.82983,465.19214,380.74225]}]}}}}},"disappear":{"slots":{"Bulb_on_01_Buttom":{"attachment":[{"time":0.2667},{"time":0.4333,"name":"Bulb_on_01_Buttom"},{"time":0.5667},{"time":0.7667,"name":"Bulb_on_01_Buttom"}]},"Bulb_on_01_L":{"attachment":[{"time":0.2667},{"time":0.4333,"name":"Bulb_on_01_L"},{"time":0.5667},{"time":0.7667,"name":"Bulb_on_01_L"}]},"Bulb_on_01_R":{"attachment":[{"time":0.2667},{"time":0.4333,"name":"Bulb_on_01_R"},{"time":0.5667},{"time":0.7667,"name":"Bulb_on_01_R"}]},"Bulb_on_01_Top":{"attachment":[{"time":0.2667},{"time":0.4333,"name":"Bulb_on_01_Top"},{"time":0.5667},{"time":0.7667,"name":"Bulb_on_01_Top"}]},"Bulb_on_02_Bottom":{"attachment":[{"time":0.1333},{"time":0.2667,"name":"Bulb_on_02_Bottom"},{"time":0.4333},{"time":0.5667,"name":"Bulb_on_02_Bottom"}]},"Bulb_on_02_L":{"attachment":[{"time":0.1333},{"time":0.2667,"name":"Bulb_on_02_L"},{"time":0.4333},{"time":0.5667,"name":"Bulb_on_02_L"}]},"Bulb_on_02_R":{"attachment":[{"time":0.1333},{"time":0.2667,"name":"Bulb_on_02_R"},{"time":0.4333},{"time":0.5667,"name":"Bulb_on_02_R"}]},"Bulb_on_02_Top":{"attachment":[{"time":0.1333},{"time":0.2667,"name":"Bulb_on_02_Top"},{"time":0.4333},{"time":0.5667,"name":"Bulb_on_02_Top"}]},"epic_glow":{"attachment":[{}]},"green smoke2":{"rgba":[{"color":"ffffff00"}]},"smoke_2.2":{"rgba":[{"color":"ffffff00"}]},"win_glow":{"attachment":[{}]}},"bones":{"main":{"scale":[{"curve":[0.093,1,0.174,1.388,0.093,1,0.174,1.388]},{"time":0.2667,"x":1.502,"y":1.502,"curve":[0.327,1.576,0.41,1.6,0.327,1.576,0.41,1.6]},{"time":0.4667,"x":1.502,"y":1.502,"curve":[0.571,1.321,0.663,0.501,0.571,1.321,0.663,0.501]},{"time":0.7667,"x":0,"y":0}]},"glows":{"scale":[{"time":0.0667,"curve":[0.136,1,0.197,1.201,0.136,1,0.197,1.201]},{"time":0.2667,"x":1.325,"y":1.325,"curve":[0.313,1.408,0.389,1.479,0.313,1.408,0.389,1.479]},{"time":0.4333,"x":1.387,"y":1.387,"curve":[0.528,1.192,0.607,0,0.528,1.192,0.607,0]},{"time":0.7,"x":0,"y":0}]},"epic_win":{"scale":[{"time":0.1,"curve":[0.143,1,0.323,1.2,0.143,1,0.323,1.2]},{"time":0.5333,"x":1.2,"y":1.2,"curve":[0.638,1.2,0.729,0,0.638,1.2,0.729,0]},{"time":0.8333,"x":0,"y":0}]},"star_mask":{"rotate":[{"value":17.61}],"translate":[{"x":373.26,"y":9.84}]}},"attachments":{"default":{"green smoke1":{"green smoke":{"deform":[{"offset":22,"vertices":[83.00403,-3.68909,90.3822,-51.64703,0,0,0,0,0,0,0,0,0,0,0,0,0,0,0,0,0,0,0,0,0,0,0,0,0,0,0,0,0,0,0,0,0,0,0,0,0,0,0,0,0,0,0,0,0,0,0,0,0,0,0,0,0,0,0,0,0,0,0,0,0,0,0,0,0,0,29.51257,1.8446,116.20569,-18.44543,130.96191,-23.97906,60.86963,-22.13446,53.49146,3.68909],"curve":[0.044,0,0.087,1]},{"time":0.1333,"curve":[0.284,0,0.576,0.67]},{"time":0.6,"vertices":[108.46857,36.15625,30.00717,66.68262,131.18268,178.87964,30.24454,136.77539,56.75543,88.68591,0,0,71.38013,145.30963,91.77466,203.9433,104.52087,84.12656,216.68982,81.57733,180.96399,33.93076,203.58484,-173.42407,183.3374,-214.1966,61.54846,-107.26996,96.71869,-87.92615,33.41205,-135.40637,15.82666,-131.88928,125.44542,-186.3761,41.21777,-51.97034,86.01965,-130.8216,-44.75146,-183.92761,-177.52979,-175.21136,-351.94214,-172.31247,-506.55994,36.479,-180.99963,71.38013,-288.1996,90.69714,-229.0188,131.91174,-11.4939,168.47803,84.03015,67.21478,-153.93042,-47.22577,-84.01147,-26.6378,0,0,47.12842,18.44152,0,0,96.03602,-183.5982,54.23441,-115.42734,-121.08038,-21.65088,90.38657,-118.63251,35.69006,66.28162,40.78857,53.53508,12.74658,30.59155,-28.04224,119.81665,0,0,-50.98584,-112.16891,81.57764,50.98576,62.2063,122.52789,62.20996,102.71875,145.14832,-81.05695,339.56458,-130.35675,72.729,-136.99872,86.66919,-9.60333,-28.93494,-62.20996,3.51703,-80.89209,-58.03143,-82.65057,117.82114,66.82404,-27.91754,6.98883,39.54419,62.14087,45.25342,56.0239,97.37732,99.19263,-9.23458,-8.47449,12.54456,-25.08905,-49.81812,-63.30713,16.85333,-65.0155,-26.88116,26.8812,84.2276,-37.63367,71.68317,-23.29706,0,0,7.5061,-92.57578,-7.97864,-134.07309,55.8009,-63.07092,90.74146,-219.84726,-112.49951,-95.50296,-133.18896,38.93221,-45.37799,-32.95087,-211.04529,126.28317,62.14087,-96.03571,84.73749,-115.80798],"curve":[0.636,0,0.665,1]},{"time":0.7,"vertices":[61.01355,20.33789,16.87903,37.50897,73.79026,100.61981,17.01257,76.93616,31.92493,49.88586,0,0,40.15137,81.73669,51.62317,114.71814,58.79297,47.32117,121.88806,45.88726,101.79224,19.08606,114.51648,-97.55109,103.12732,-120.4856,34.62097,-60.33936,54.4043,-49.45844,18.79428,-76.16608,8.9025,-74.18774,70.56306,-104.83661,23.185,-29.23334,48.38611,-73.58716,-25.17273,-103.45935,-99.8606,-98.5564,-197.9674,-96.92581,-284.93982,20.51944,-101.81226,40.15134,-162.1123,51.01715,-128.82312,74.20038,-6.46533,94.76892,47.26697,37.80835,-86.58594,-26.56451,-47.25647,-14.98376,0,0,26.50977,10.37336,0,0,54.02028,-103.27399,30.50687,-64.92789,-68.10773,-12.17865,50.84247,-66.7308,20.07562,37.28345,22.9436,30.11349,7.16992,17.20776,-15.77368,67.39687,0,0,-28.67957,-63.09503,45.88745,28.6795,34.99109,68.92197,34.99304,57.77933,81.646,-45.59454,191.00513,-73.32568,40.91003,-77.06183,48.75146,-5.40192,-16.27588,-34.9931,1.97833,-45.50183,-32.6427,-46.49097,66.27438,37.5885,-15.70362,3.93121,22.24362,34.95422,25.45504,31.51343,54.77475,55.79584,-5.19446,-4.76691,7.05634,-14.11261,-28.02271,-35.61029,9.48004,-36.57123,-15.12067,15.12067,47.37805,-21.16895,40.32178,-13.10461,0,0,4.22217,-52.07388,-4.48804,-75.41611,31.38806,-35.47742,51.04211,-123.66409,-63.28101,-53.72043,-74.91882,21.89938,-25.52515,-18.53485,-118.71301,71.03427,34.95424,-54.02011,47.66486,-65.142]}]}},"green smoke2":{"green smoke":{"deform":[{"vertices":[26.03119,-304.93884,84.18448,-342.8698,32.60356,-272.60345,68.23059,-239.67752,85.53149,-262.17303,37.87622,-451.13452,-24.17224,-230.56348,-74.2229,-207.82355,-124.06641,-39.85138,-223.12598,-7.4375,-44.62512,206.39159,1.85938,223.126,0,0,0,0,32.65808,133.60077,11.87585,124.69409,35.62711,133.60083,53.44024,124.69415,68.28491,71.25378,47.50244,100.94281,-14.84436,139.5387,59.37842,172.19635,0,0,89.06738,11.87568,136.56982,2.96899,248.33972,-151.9877,210.6466,-217.4256,132.01611,-288.2044,37.18768,-290.0639,20.78247,-133.6009,292.00793,-9.59552,0,0,65.31592,56.4093,0,0,26.7202,-157.35205,108.86243,-171.80658,89.25031,-204.5321,-8.84576,-254.39973,-46.36261,-267.83624,-289.72803,-6.54176,-20.50757,-91.62195,-166.25879,17.8135,-240.12158,73.44255,-157.35205,-44.53365,0,0,-20.45349,89.25038,26.72009,139.53867,100.94312,163.28989,65.31604,192.97894,20.78235,124.69415,44.5332,118.75626,59.3783,136.56973,26.72046,89.06726,83.12933,163.28995,109.84967,109.84955,44.53364,133.60095,50.47137,145.47638,41.56478,115.78741,8.90695,103.91174,50.47138,62.34714,83.12933,59.37811,32.6582,181.10352,56.40924,187.04144,0,0,50.47156,62.34705,38.59595,100.94293,29.68927,124.69409,-5.93762,118.75607,14.84448,103.91162,29.68896,145.4765,71.25415,89.0672,38.59607,187.04121,68.28491,44.5336,137.59412,-178.5007,125.29779,-221.44318,52.2697,-253.29005,102.8327,-354.026],"curve":[0.033,0,0.064,1]},{"time":0.1,"curve":[0.25,0,0.532,0.67]},{"time":0.5667,"vertices":[26.03119,-304.93884,84.18448,-342.8698,32.60356,-272.60345,68.23059,-239.67752,85.53149,-262.17303,37.87622,-451.13452,-24.17224,-230.56348,-74.2229,-207.82355,-124.06641,-39.85138,-223.12598,-7.4375,-44.62512,206.39159,1.85938,223.126,0,0,0,0,32.65808,133.60077,11.87585,124.69409,35.62711,133.60083,53.44024,124.69415,68.28491,71.25378,47.50244,100.94281,-14.84436,139.5387,59.37842,172.19635,0,0,89.06738,11.87568,136.56982,2.96899,248.33972,-151.9877,210.6466,-217.4256,132.01611,-288.2044,37.18768,-290.0639,20.78247,-133.6009,292.00793,-9.59552,0,0,65.31592,56.4093,0,0,26.7202,-157.35205,108.86243,-171.80658,89.25031,-204.5321,-8.84576,-254.39973,-46.36261,-267.83624,-289.72803,-6.54176,-20.50757,-91.62195,-166.25879,17.8135,-240.12158,73.44255,-157.35205,-44.53365,0,0,-20.45349,89.25038,26.72009,139.53867,100.94312,163.28989,65.31604,192.97894,20.78235,124.69415,44.5332,118.75626,59.3783,136.56973,26.72046,89.06726,83.12933,163.28995,109.84967,109.84955,44.53364,133.60095,50.47137,145.47638,41.56478,115.78741,8.90695,103.91174,50.47138,62.34714,83.12933,59.37811,32.6582,181.10352,56.40924,187.04144,0,0,50.47156,62.34705,38.59595,100.94293,29.68927,124.69409,-5.93762,118.75607,14.84448,103.91162,29.68896,145.4765,71.25415,89.0672,38.59607,187.04121,68.28491,44.5336,137.59412,-178.5007,125.29779,-221.44318,52.2697,-253.29005,102.8327,-354.026],"curve":[0.618,0,0.654,1]},{"time":0.7,"vertices":[10.71875,-125.56305,34.66418,-141.1817,13.425,-112.24847,28.09497,-98.69073,35.21887,-107.95361,15.59607,-185.76129,-9.95325,-94.93793,-30.56238,-85.5744,-51.08618,-16.40939,-91.87537,-3.0625,-18.375,84.98477,0.76563,91.87543,0,0,0,0,13.44745,55.01208,4.89005,51.3446,14.66998,55.01208,22.0048,51.34467,28.11731,29.33978,19.55981,41.5647,-6.11243,57.45709,24.44995,70.90436,0,0,36.6748,4.88998,56.23462,1.22253,102.25757,-62.58319,86.73682,-89.5282,54.35962,-118.67242,15.31256,-119.43811,8.5575,-55.01215,120.23853,-3.9511,0,0,26.89478,23.22736,0,0,11.00244,-64.79202,44.82571,-70.7439,36.75012,-84.21912,-3.6424,-104.75287,-19.09045,-110.28552,-119.2998,-2.69366,-8.44434,-37.72668,-68.45947,7.33498,-98.87354,30.24104,-64.79199,-18.33738,0,0,-8.422,36.75015,11.00244,57.45709,41.56482,67.237,26.8949,79.46191,8.5575,51.34467,18.33716,48.89966,24.44995,56.23462,11.00256,36.67474,34.22974,67.23706,45.23221,45.23218,18.33738,55.01215,20.78233,59.90204,17.1149,47.67719,3.66757,42.78723,20.78234,25.67236,34.22974,24.44983,13.44751,74.57202,23.22736,77.01709,0,0,20.78241,25.6723,15.89246,41.56473,12.22501,51.3446,-2.44495,48.89957,6.11243,42.78714,12.22485,59.9021,29.33997,36.67474,15.89246,77.01697,28.11731,18.33736,56.65637,-73.50031,51.59326,-91.1825,21.52283,-104.29593,42.3429,-145.77542]}]}},"smoke_2":{"Effects_02":{"deform":[{"time":0.1333,"curve":[0.284,0,0.579,0.67]},{"time":0.6,"offset":4,"vertices":[47.80103,-38.99274,30.28422,-47.10858,68.9803,-75.71008,79.0752,-146.37317,0,0,0,0,-115.89502,-2.79266,-113.04004,46.42716,0,0,-66.6134,306.982,0,0,0,0,-36.12939,80.33276,19.3396,148.76477,0,0,0,0,0,0,0,0,13.05078,-78.38449,-16.25867,-28.08313,33.99548,8.86826,0,0,0,0,59.68829,-151.94104,21.57288,-75.69507,28.08301,-16.25864,-38.42953,-56.16626,23.55432,-35.33136,30.2691,-61.62244,109.76636,-83.59274,-2.61255,-75.64154,-37.0625,-46.44952,-118.75342,-7.8223,-61.82971,47.71704,-89.03137,139.58919,0,0,0,0,16.26897,40.17328,78.78018,-11.69922,39.96298,-65.80017,61.12436,-41.46179,65.62384,-25.75912,26.89874,-17.94431,40.73535,-34.21759,0,0,58.19031,30.36026,-43.0105,-101.20068,-20.23999,-68.3103,5.05981,-146.74084,20.24048,-63.25031,45.54004,-37.95026,50.6001,53.1304,58.19031,-7.59015,40.48022,83.49048,60.72034,15.18011,53.13037,32.89022,56.05884,86.36093,56.0589,86.36093,56.05884,86.36093,-6.91705,53.99176,-3.8623,102.30731,-45.14984,86.54919,-57.50299,76.99768,-39.75415,60.47839,0,0,0,0,0,0,0,0,88.55066,111.32068,214.87915,72.1761,184.46814,-65.45648,37.19128,-65.45652,0,0,0,0,-38.67883,60.99353,65.45654,77.3577,-16.36414,-75.87012,31.2406,-63.96887,77.35767,-35.70355,69.9198,-19.33946,159.17822,-41.65414,22.3147,34.21591,50.30902,82.65082,0,0,0,0,0,0,43.20793,56.61737,0,73.00656,123.66412,178.79166,120.68448,56.61743,117.70468,11.91951,89.39589,-116.21468,-171.97998,41.98453,-93.56592,104.94553,-90.45691,74.72424,-118.79199,-15.2973,-102.35474,54.60861,-50.57617,-93.63861,7.88715,-70.17468,-164.43494,0.7774,-144.43237,-88.18719,-98.30237,-78.20651,-85.95886,-137.83063,-49.5191,-158.80737,-0.52844,-126.41992,150.06189,135.288,28.14954,232.58075,63.8844,107.00763,15.9704,200.63986,225.2616,101.94949,80.45581,-30.67883,120.98285,0.5318,-45.12024,25.95251,140.08197,-48.58023,-53.21643,-30.83566],"curve":[0.631,0,0.665,1]},{"time":0.7,"offset":4,"vertices":[29.87561,-24.37048,18.92764,-29.44287,43.11267,-47.31879,49.422,-91.48322,0,0,0,0,-72.43433,-1.74542,-70.65002,29.01698,0,0,-41.63336,191.86377,0,0,0,0,-22.58087,50.20801,12.08728,92.97797,0,0,0,0,0,0,0,0,8.15674,-48.99026,-10.16168,-17.55194,21.24719,5.54266,0,0,0,0,37.30518,-94.96313,13.48303,-47.30942,17.55188,-10.16165,-24.01846,-35.10394,14.72147,-22.08209,18.91821,-38.51404,68.604,-52.24545,-1.63281,-47.27597,-23.16406,-29.03094,-74.22083,-4.88895,-38.64355,29.82316,-55.64465,87.24324,0,0,0,0,10.16811,25.10828,49.23761,-7.31201,24.97687,-41.12512,38.20273,-25.91364,41.01489,-16.09946,16.81171,-11.21521,25.45959,-21.38599,0,0,36.36896,18.97516,-26.88159,-63.25043,-12.65002,-42.69394,3.16235,-91.71301,12.65027,-39.53143,28.46252,-23.71893,31.625,33.20651,36.3689,-4.74384,25.30017,52.18155,37.9502,9.48758,33.20642,20.5564,35.03674,53.97559,35.0368,53.97559,35.0368,53.97559,-4.32318,33.74487,-2.41394,63.94208,-28.21869,54.09326,-35.93933,48.12354,-24.84631,37.79901,0,0,0,0,0,0,0,0,55.34412,69.57541,134.29944,45.11006,115.2926,-40.9103,23.24451,-40.91032,0,0,0,0,-24.17432,38.12097,40.91028,48.3486,-10.22754,-47.41882,19.52539,-39.98053,48.34851,-22.31473,43.69983,-12.08716,99.48633,-26.03384,13.94666,21.38492,31.44315,51.65675,0,0,0,0,0,0,27.00496,35.38586,0,45.62909,77.29008,111.74484,75.42782,35.38589,73.56543,7.44969,55.87242,-72.63418,-107.48755,26.24033,-58.47864,65.59097,-56.53552,46.70267,-74.245,-9.56082,-63.97168,34.13037,-31.61011,-58.52414,4.92944,-43.85918,-102.77185,0.48587,-90.27026,-55.117,-61.43896,-48.87909,-53.72424,-86.14414,-30.94946,-99.25461,-0.33026,-79.01246,93.7887,84.55502,17.59344,145.36298,39.92773,66.87979,9.98151,125.39993,140.78851,63.71848,50.28491,-19.17429,75.61429,0.33237,-28.20013,16.22031,87.55127,-30.36264,-33.26025,-19.27228]}]}},"smoke_2.2":{"Effects_02":{"deform":[{"offset":2,"vertices":[-57.98352,157.38373,4.1416,70.40857,45.55834,80.7627,84.80777,80.61163,0,0,0,0,53.84167,113.896,68.33752,-2.07077,87.68628,19.35338,0,0,-35.53882,-40.12451,-26.36761,-91.71313,8.83984,-18.94263,-44.19934,-66.93033,20.20544,-61.87888,0,0,-5.46155,-54.32252,0,0,66.03174,127.07318,25.39191,96.01056,20.12451,89.03354,-13.23157,35.91425,-33.07898,25.51794,-58.5968,2.83537,-2.37762,94.25897,2.0708,87.10123,12.64758,125.58621,32.0498,119.73492,24.2662,124.05728,14.42432,93.39783,54.81653,96.40128,56.89978,96.14917,107.93579,24.08553,104.19739,16.88576,81.33411,-37.17847,149.69666,-16.30824,0,0,0,0,0,74.55011,-4.14163,99.40024,6.21268,99.40024,4.14185,80.7627,12.4248,66.26685,14.49591,62.12515,0,0,0,0,0,0,0,0,0,0,6.2124,84.90436,-8.2832,91.11685,-8.28345,97.32944,16.56665,84.90427,-10.35437,74.55023,-57.98352,20.70844,0,0,0,0,-27.78235,-20.20535,12.6283,-51.77631,2.52563,-45.46216,0,0,10.10266,-35.35944,42.93652,-55.56479,5.05127,-41.67358,0,-68.33777,0,0,0,0,0,0,0,0,0,0,-22.77917,-37.27509,-138.74622,-53.8418,0,0,-65.66748,-16.4169,0,0,0,0,-2.52563,-49.25064,-31.57092,-34.09665,-72.38318,-67.48157,-33.13342,-26.9209,-70.40869,26.92102,-49.70032,-4.14172,-15.15405,-40.41074,0,0,0,0,63.05278,-40.12453,0,0,43.56378,-57.32074,0,0,2.29282,-48.14941,33.24604,-69.93134,10.31778,-28.66045,-35.53888,-2.2928,54.51953,-95.1424,-38.23437,-96.39444,-5.73206,-53.88156,18.34265,-45.8566,-8.02502,-22.92838,0,0,0,0,31.49561,-85.1759,-13.75684,-61.90646,28.66028,-25.22113,53.88147,-18.34262,30.95325,-38.97815,0,0,-6.87854,-44.71021,17.19617,-42.41739,0,0,0,0,22.92834,-42.41736,17.19629,-40.1246,-14.90332,-33.24603,-17.19629,-38.97815,0,0,-36.62231,-56.82767],"curve":"stepped"},{"time":0.2667,"offset":2,"vertices":[-57.98352,157.38373,4.1416,70.40857,45.55834,80.7627,84.80777,80.61163,0,0,0,0,53.84167,113.896,68.33752,-2.07077,87.68628,19.35338,0,0,-35.53882,-40.12451,-26.36761,-91.71313,8.83984,-18.94263,-44.19934,-66.93033,20.20544,-61.87888,0,0,-5.46155,-54.32252,0,0,66.03174,127.07318,25.39191,96.01056,20.12451,89.03354,-13.23157,35.91425,-33.07898,25.51794,-58.5968,2.83537,-2.37762,94.25897,2.0708,87.10123,12.64758,125.58621,32.0498,119.73492,24.2662,124.05728,14.42432,93.39783,54.81653,96.40128,56.89978,96.14917,107.93579,24.08553,104.19739,16.88576,81.33411,-37.17847,149.69666,-16.30824,0,0,0,0,0,74.55011,-4.14163,99.40024,6.21268,99.40024,4.14185,80.7627,12.4248,66.26685,14.49591,62.12515,0,0,0,0,0,0,0,0,0,0,6.2124,84.90436,-8.2832,91.11685,-8.28345,97.32944,16.56665,84.90427,-10.35437,74.55023,-57.98352,20.70844,0,0,0,0,-27.78235,-20.20535,12.6283,-51.77631,2.52563,-45.46216,0,0,10.10266,-35.35944,42.93652,-55.56479,5.05127,-41.67358,0,-68.33777,0,0,0,0,0,0,0,0,0,0,-22.77917,-37.27509,-138.74622,-53.8418,0,0,-65.66748,-16.4169,0,0,0,0,-2.52563,-49.25064,-31.57092,-34.09665,-72.38318,-67.48157,-33.13342,-26.9209,-70.40869,26.92102,-49.70032,-4.14172,-15.15405,-40.41074,0,0,0,0,63.05278,-40.12453,0,0,43.56378,-57.32074,0,0,2.29282,-48.14941,33.24604,-69.93134,10.31778,-28.66045,-35.53888,-2.2928,54.51953,-95.1424,-38.23437,-96.39444,-5.73206,-53.88156,18.34265,-45.8566,-8.02502,-22.92838,0,0,0,0,31.49561,-85.1759,-13.75684,-61.90646,28.66028,-25.22113,53.88147,-18.34262,30.95325,-38.97815,0,0,-6.87854,-44.71021,17.19617,-42.41739,0,0,0,0,22.92834,-42.41736,17.19629,-40.1246,-14.90332,-33.24603,-17.19629,-38.97815,0,0,-36.62231,-56.82767],"curve":[0.411,0,0.561,1]},{"time":0.7,"offset":2,"vertices":[-3.41077,9.25787,0.24359,4.14172,2.6799,4.75073,4.98871,4.74188,0,0,0,0,3.16711,6.69977,4.0199,-0.12183,5.15808,1.13844,0,0,-2.09052,-2.36029,-1.55103,-5.3949,0.51999,-1.11426,-2.59998,-3.93707,1.1886,-3.63995,0,0,-0.32129,-3.19544,0,0,3.88428,7.47491,1.49365,5.64771,1.18378,5.2373,-0.77832,2.11261,-1.9458,1.50107,-3.4469,0.16678,-0.13983,5.54465,0.12183,5.12363,0.74399,7.38745,1.88528,7.04327,1.42743,7.29749,0.84851,5.49402,3.22449,5.67068,3.34705,5.65585,6.34912,1.41681,6.12927,0.99329,4.78442,-2.18698,8.80566,-0.95932,0,0,0,0,0,4.38531,-0.24362,5.84711,0.36545,5.84711,0.24365,4.75073,0.7309,3.89807,0.85272,3.65445,0,0,0,0,0,0,0,0,0,0,0.36548,4.99438,-0.48718,5.35983,-0.4873,5.72528,0.97449,4.99438,-0.60913,4.38531,-3.41077,1.21814,0,0,0,0,-1.63428,-1.18857,0.74286,-3.04568,0.14856,-2.67426,0,0,0.5943,-2.07999,2.5257,-3.26849,0.29712,-2.45139,0,-4.01987,0,0,0,0,0,0,0,0,0,0,-1.33997,-2.19266,-8.16162,-3.16718,0,0,-3.86279,-0.9657,0,0,0,0,-0.14856,-2.89709,-1.85718,-2.00571,-4.25781,-3.96951,-1.94897,-1.58359,-4.14172,1.5836,-2.92358,-0.24364,-0.89148,-2.37711,0,0,0,0,3.709,-2.36028,0,0,2.56258,-3.37183,0,0,0.13488,-2.83231,1.95566,-4.11362,0.60692,-1.68591,-2.09052,-0.13488,3.20703,-5.59662,-2.24902,-5.67029,-0.33716,-3.16953,1.07898,-2.69745,-0.47205,-1.34875,0,0,0,0,1.85266,-5.01035,-0.8092,-3.64157,1.68591,-1.48361,3.16956,-1.07898,1.8208,-2.29285,0,0,-0.4046,-2.63,1.01154,-2.49515,0,0,0,0,1.34875,-2.49515,1.01154,-2.36029,-0.87665,-1.95566,-1.01154,-2.29285,0,0,-2.15424,-3.34283]}]}},"star_glow":{"star_glow":{"deform":[{"vertices":[591.19495,109.38898,-404.13788,-343.01678,-522.60376,-76.82983,465.19214,380.74225]}]}}}}},"idle":{"slots":{"Bulb_on_01_Buttom":{"attachment":[{"time":0.3},{"time":0.4667,"name":"Bulb_on_01_Buttom"},{"time":0.6},{"time":0.7667,"name":"Bulb_on_01_Buttom"},{"time":0.9},{"time":1.0667,"name":"Bulb_on_01_Buttom"},{"time":1.2},{"time":1.3667,"name":"Bulb_on_01_Buttom"}]},"Bulb_on_01_L":{"attachment":[{"time":0.3},{"time":0.4667,"name":"Bulb_on_01_L"},{"time":0.6},{"time":0.7667,"name":"Bulb_on_01_L"},{"time":0.9},{"time":1.0667,"name":"Bulb_on_01_L"},{"time":1.2},{"time":1.3667,"name":"Bulb_on_01_L"}]},"Bulb_on_01_R":{"attachment":[{"time":0.3},{"time":0.4667,"name":"Bulb_on_01_R"},{"time":0.6},{"time":0.7667,"name":"Bulb_on_01_R"},{"time":0.9},{"time":1.0667,"name":"Bulb_on_01_R"},{"time":1.2},{"time":1.3667,"name":"Bulb_on_01_R"}]},"Bulb_on_01_Top":{"attachment":[{"time":0.3},{"time":0.4667,"name":"Bulb_on_01_Top"},{"time":0.6},{"time":0.7667,"name":"Bulb_on_01_Top"},{"time":0.9},{"time":1.0667,"name":"Bulb_on_01_Top"},{"time":1.2},{"time":1.3667,"name":"Bulb_on_01_Top"}]},"Bulb_on_02_Bottom":{"attachment":[{"time":0.1667},{"time":0.3,"name":"Bulb_on_02_Bottom"},{"time":0.4667},{"time":0.6,"name":"Bulb_on_02_Bottom"},{"time":0.7667},{"time":0.9,"name":"Bulb_on_02_Bottom"},{"time":1.0667},{"time":1.2,"name":"Bulb_on_02_Bottom"},{"time":1.3667},{"time":1.5,"name":"Bulb_on_02_Bottom"}]},"Bulb_on_02_L":{"attachment":[{"time":0.1667},{"time":0.3,"name":"Bulb_on_02_L"},{"time":0.4667},{"time":0.6,"name":"Bulb_on_02_L"},{"time":0.7667},{"time":0.9,"name":"Bulb_on_02_L"},{"time":1.0667},{"time":1.2,"name":"Bulb_on_02_L"},{"time":1.3667},{"time":1.5,"name":"Bulb_on_02_L"}]},"Bulb_on_02_R":{"attachment":[{"time":0.1667},{"time":0.3,"name":"Bulb_on_02_R"},{"time":0.4667},{"time":0.6,"name":"Bulb_on_02_R"},{"time":0.7667},{"time":0.9,"name":"Bulb_on_02_R"},{"time":1.0667},{"time":1.2,"name":"Bulb_on_02_R"},{"time":1.3667},{"time":1.5,"name":"Bulb_on_02_R"}]},"Bulb_on_02_Top":{"attachment":[{"time":0.1667},{"time":0.3,"name":"Bulb_on_02_Top"},{"time":0.4667},{"time":0.6,"name":"Bulb_on_02_Top"},{"time":0.7667},{"time":0.9,"name":"Bulb_on_02_Top"},{"time":1.0667},{"time":1.2,"name":"Bulb_on_02_Top"},{"time":1.3667},{"time":1.5,"name":"Bulb_on_02_Top"}]},"epic_glow":{"attachment":[{}]},"green smoke1":{"rgba":[{"color":"ffffffff"},{"time":1.5,"color":"ffffff00"}]},"green smoke2":{"rgba":[{"color":"ffffff00"},{"time":1.5,"color":"ffffffff"}]},"smoke_2":{"rgba":[{"color":"ffffffff"},{"time":1.5,"color":"ffffff00"}]},"smoke_2.2":{"rgba":[{"color":"ffffff00"},{"time":1.5,"color":"ffffffff"}]},"win_glow":{"attachment":[{}]}},"bones":{"star_mask":{"rotate":[{"value":17.61}],"translate":[{"x":373.26,"y":9.84,"curve":"stepped"},{"time":0.4667,"x":373.26,"y":9.84,"curve":[0.766,373.26,1.067,3918.94,0.766,9.84,1.067,1135.24]},{"time":1.3667,"x":3918.94,"y":1135.24}]}},"attachments":{"default":{"green smoke1":{"green smoke":{"deform":[{"offset":22,"vertices":[83.00403,-3.68909,90.3822,-51.64703,0,0,0,0,0,0,0,0,0,0,0,0,0,0,0,0,0,0,0,0,0,0,0,0,0,0,0,0,0,0,0,0,0,0,0,0,0,0,0,0,0,0,0,0,0,0,0,0,0,0,0,0,0,0,0,0,0,0,0,0,0,0,0,0,0,0,29.51257,1.8446,116.20569,-18.44543,130.96191,-23.97906,60.86963,-22.13446,53.49146,3.68909]},{"time":1.5,"vertices":[123.32123,168.47968,55.6618,257.06622,131.18268,178.87964,30.24454,136.77539,56.75543,88.68591,0,0,71.38013,145.30963,91.77466,203.9433,311.8827,193.56747,356.85144,133.41782,392.1659,28.17076,359.1062,-121.58368,202.53748,-314.0374,119.14893,-266.63135,127.4389,-189.68689,85.25253,-294.7677,35.0267,-275.89044,144.64545,-330.37726,116.09845,-265.09204,86.01965,-236.42255,-44.75146,-289.52856,-244.73022,-261.612,-426.82275,-206.87271,-581.4403,1.91876,-348.0409,136.66058,-413.0005,192.45801,-319.25952,279.75287,-11.4939,168.47803,84.03015,155.53546,-153.93042,-47.22577,-239.53271,-82.31822,0,0,-43.11243,-58.35908,0,0,96.03602,-183.5982,55.58463,16.89609,-123.78082,98.52045,90.38657,-118.63251,35.69006,66.28162,121.42932,109.21559,43.4668,166.91257,-28.04224,119.81665,0,0,-50.98584,-112.16891,219.81885,77.8659,94.84668,112.92789,235.01135,31.67816,145.14832,-81.05695,270.44373,-84.27655,72.729,-136.99872,150.02954,-46.08374,26.74536,-125.57037,28.47717,-148.09265,13.00928,-144.091,137.0214,-132.85767,-8.71746,-42.93158,45.30438,-31.93994,45.25342,56.0239,130.01776,-31.36847,31.0858,-54.55487,24.0647,-149.89008,-90.13843,-128.58765,-4.26672,-180.21637,-9.2E-4,-34.55936,120.70795,-145.1546,198.40417,-107.77783,0,0,7.5061,-92.57578,-84.7793,-191.67368,38.52075,-157.15161,52.34119,-265.92764,-112.49951,-95.50296,-227.2699,-37.86852,-19.72345,53.46448,-264.80566,164.68344,62.14087,-96.03571,84.73749,-115.80798]}]}},"green smoke2":{"green smoke":{"deform":[{"vertices":[26.03119,-304.93884,84.18448,-342.8698,32.60356,-272.60345,68.23059,-239.67752,85.53149,-262.17303,37.87622,-451.13452,-24.17224,-230.56348,-74.2229,-207.82355,-124.06641,-39.85138,-223.12598,-7.4375,-44.62512,206.39159,1.85938,223.126,0,0,0,0,32.65808,133.60077,11.87585,124.69409,35.62711,133.60083,53.44024,124.69415,68.28491,71.25378,47.50244,100.94281,-14.84436,139.5387,59.37842,172.19635,0,0,89.06738,11.87568,136.56982,2.96899,248.33972,-151.9877,210.6466,-217.4256,132.01611,-288.2044,37.18768,-290.0639,20.78247,-133.6009,292.00793,-9.59552,0,0,65.31592,56.4093,0,0,26.7202,-157.35205,108.86243,-171.80658,89.25031,-204.5321,-8.84576,-254.39973,-46.36261,-267.83624,-289.72803,-6.54176,-20.50757,-91.62195,-166.25879,17.8135,-240.12158,73.44255,-157.35205,-44.53365,0,0,-20.45349,89.25038,26.72009,139.53867,100.94312,163.28989,65.31604,192.97894,20.78235,124.69415,44.5332,118.75626,59.3783,136.56973,26.72046,89.06726,83.12933,163.28995,109.84967,109.84955,44.53364,133.60095,50.47137,145.47638,41.56478,115.78741,8.90695,103.91174,50.47138,62.34714,83.12933,59.37811,32.6582,181.10352,56.40924,187.04144,0,0,50.47156,62.34705,38.59595,100.94293,29.68927,124.69409,-5.93762,118.75607,14.84448,103.91162,29.68896,145.4765,71.25415,89.0672,38.59607,187.04121,68.28491,44.5336,137.59412,-178.5007,125.29779,-221.44318,52.2697,-253.29005,102.8327,-354.026]},{"time":1.5,"offset":22,"vertices":[83.00403,-3.68909,90.3822,-51.64703,0,0,0,0,0,0,0,0,0,0,0,0,0,0,0,0,0,0,0,0,0,0,0,0,0,0,0,0,0,0,0,0,0,0,0,0,0,0,0,0,0,0,0,0,0,0,0,0,0,0,0,0,0,0,0,0,0,0,0,0,0,0,0,0,0,0,29.51257,1.8446,116.20569,-18.44543,130.96191,-23.97906,60.86963,-22.13446,53.49146,3.68909]}]}},"smoke_2":{"Effects_02":{"deform":[{},{"time":1.5,"offset":4,"vertices":[47.80103,-38.99274,30.28422,-47.10858,68.9803,-75.71008,79.0752,-146.37317,0,0,0,0,-115.89502,-2.79266,-113.04004,46.42716,0,0,-66.6134,306.982,0,0,0,0,-36.12939,80.33276,19.3396,148.76477,0,0,0,0,0,0,0,0,13.05078,-78.38449,-16.25867,-28.08313,33.99548,8.86826,0,0,0,0,59.68829,-151.94104,21.57288,-75.69507,28.08301,-16.25864,-38.42953,-56.16626,23.55432,-35.33136,30.2691,-61.62244,109.76636,-83.59274,-2.61255,-75.64154,-37.0625,-46.44952,-118.75342,-7.8223,-61.82971,47.71704,-89.03137,139.58919,0,0,0,0,16.26897,40.17328,78.78018,-11.69922,39.96298,-65.80017,61.12436,-41.46179,65.62384,-25.75912,26.89874,-17.94431,40.73535,-34.21759,0,0,58.19031,30.36026,-43.0105,-101.20068,-20.23999,-68.3103,5.05981,-146.74084,20.24048,-63.25031,45.54004,-37.95026,50.6001,53.1304,58.19031,-7.59015,40.48022,83.49048,60.72034,15.18011,53.13037,32.89022,56.05884,86.36093,56.0589,86.36093,56.05884,86.36093,-6.91705,53.99176,-3.8623,102.30731,-45.14984,86.54919,-57.50299,76.99768,-39.75415,60.47839,0,0,0,0,0,0,0,0,88.55066,111.32068,214.87915,72.1761,184.46814,-65.45648,37.19128,-65.45652,0,0,0,0,-38.67883,60.99353,65.45654,77.3577,-16.36414,-75.87012,31.2406,-63.96887,77.35767,-35.70355,69.9198,-19.33946,159.17822,-41.65414,22.3147,34.21591,50.30902,82.65082,0,0,0,0,0,0,43.20793,56.61737,0,73.00656,123.66412,178.79166,120.68448,56.61743,117.70468,11.91951,89.39589,-116.21468,-171.97998,41.98453,-93.56592,104.94553,-90.45691,74.72424,-118.79199,-15.2973,-102.35474,54.60861,-50.57617,-93.63861,7.88715,-70.17468,-164.43494,0.7774,-144.43237,-88.18719,-98.30237,-78.20651,-85.95886,-137.83063,-49.5191,-158.80737,-0.52844,-126.41992,150.06189,135.288,28.14954,232.58075,63.8844,107.00763,15.9704,200.63986,225.2616,101.94949,80.45581,-30.67883,120.98285,0.5318,-45.12024,25.95251,140.08197,-48.58023,-53.21643,-30.83566]}]}},"smoke_2.2":{"Effects_02":{"deform":[{"offset":2,"vertices":[-57.98352,157.38373,4.1416,70.40857,45.55834,80.7627,84.80777,80.61163,0,0,0,0,53.84167,113.896,68.33752,-2.07077,87.68628,19.35338,0,0,-35.53882,-40.12451,-26.36761,-91.71313,8.83984,-18.94263,-44.19934,-66.93033,20.20544,-61.87888,0,0,-5.46155,-54.32252,0,0,66.03174,127.07318,25.39191,96.01056,20.12451,89.03354,-13.23157,35.91425,-33.07898,25.51794,-58.5968,2.83537,-2.37762,94.25897,2.0708,87.10123,12.64758,125.58621,32.0498,119.73492,24.2662,124.05728,14.42432,93.39783,54.81653,96.40128,56.89978,96.14917,107.93579,24.08553,104.19739,16.88576,81.33411,-37.17847,149.69666,-16.30824,0,0,0,0,0,74.55011,-4.14163,99.40024,6.21268,99.40024,4.14185,80.7627,12.4248,66.26685,14.49591,62.12515,0,0,0,0,0,0,0,0,0,0,6.2124,84.90436,-8.2832,91.11685,-8.28345,97.32944,16.56665,84.90427,-10.35437,74.55023,-57.98352,20.70844,0,0,0,0,-27.78235,-20.20535,12.6283,-51.77631,2.52563,-45.46216,0,0,10.10266,-35.35944,42.93652,-55.56479,5.05127,-41.67358,0,-68.33777,0,0,0,0,0,0,0,0,0,0,-22.77917,-37.27509,-138.74622,-53.8418,0,0,-65.66748,-16.4169,0,0,0,0,-2.52563,-49.25064,-31.57092,-34.09665,-72.38318,-67.48157,-33.13342,-26.9209,-70.40869,26.92102,-49.70032,-4.14172,-15.15405,-40.41074,0,0,0,0,63.05278,-40.12453,0,0,43.56378,-57.32074,0,0,2.29282,-48.14941,33.24604,-69.93134,10.31778,-28.66045,-35.53888,-2.2928,54.51953,-95.1424,-38.23437,-96.39444,-5.73206,-53.88156,18.34265,-45.8566,-8.02502,-22.92838,0,0,0,0,31.49561,-85.1759,-13.75684,-61.90646,28.66028,-25.22113,53.88147,-18.34262,30.95325,-38.97815,0,0,-6.87854,-44.71021,17.19617,-42.41739,0,0,0,0,22.92834,-42.41736,17.19629,-40.1246,-14.90332,-33.24603,-17.19629,-38.97815,0,0,-36.62231,-56.82767]},{"time":1.5}]}},"star_glow":{"star_glow":{"deform":[{"vertices":[591.19495,109.38898,-404.13788,-343.01678,-522.60376,-76.82983,465.19214,380.74225]}]}}}}}}}